<BLOCK  TYPE='AUFTRAG'>
<OBJ> <ARBEITSPROZESS>Stromzähler Wechsel RollOut</ARBEITSPROZESS><AUF_NR>Master2025000539</AUF_NR><AV_ID>WE</AV_ID><ENDGROBTERMIN>2025-12-21T00:00:00</ENDGROBTERMIN><FIXTERMIN>0</FIXTERMIN><GER_BAUFORM>5&#47;60 A</GER_BAUFORM><GER_BAUFORMTXT>DD3 BZ06 ETA 3x230&#47;400V 5(60)A</GER_BAUFORMTXT><GER_BAUJAHR>2017</GER_BAUJAHR><GER_BAUKLAS>mME DS</GER_BAUKLAS><GER_BEGLJAHR>2017</GER_BEGLJAHR><GER_ENUM>1EBZ0100020423</GER_ENUM><GER_GERAETINFO> </GER_GERAETINFO><GER_LOS>E-25-01</GER_LOS><GER_PRUEFLING>0</GER_PRUEFLING><GER_SERIALNR>1EBZ0100020423</GER_SERIALNR><GER_SPARTE>E</GER_SPARTE><GER_SPARTETXT>Elektroenergie</GER_SPARTETXT><GER_TWJAHR>2025</GER_TWJAHR><GP_ANREDE> </GP_ANREDE><GP_FAX> </GP_FAX><GP_HNUM>1</GP_HNUM><GPL_HINWEIS> Anschlussraum, Restaurant</GPL_HINWEIS><GP_MAIL> </GP_MAIL><GP_NAME_CO> </GP_NAME_CO><GP_NAME1>Maxi Muster</GP_NAME1><GP_NAME2> </GP_NAME2><GP_NR>0014705115</GP_NR><GP_ORT>Musterstadt</GP_ORT><GP_ORTSTEIL> </GP_ORTSTEIL><GP_PLZ>0811</GP_PLZ><GP_PLZ_POSTF> </GP_PLZ_POSTF><GP_POSTF> </GP_POSTF><GP_STR>Muster Weg</GP_STR><GP_TEL> </GP_TEL><GP_TYP> </GP_TYP><GP_TYPTXT> </GP_TYPTXT><GROBTERMINART>0</GROBTERMINART><HNUM>1</HNUM><NAME1>Muster, Maxi</NAME1><NAME2> </NAME2><ORT>Musterstadt</ORT><ORTSTEIL> </ORTSTEIL><PLZ>0811</PLZ><PRIOKENNZEICHEN>0</PRIOKENNZEICHEN><PROZESS>Gerätewechsel</PROZESS><RE_ANREDE> </RE_ANREDE><RE_NR> </RE_NR><RE_ZEILE1> </RE_ZEILE1><RE_ZEILE2>Maxi Muster</RE_ZEILE2><RE_ZEILE3> </RE_ZEILE3><RE_ZEILE4>Muster Weg 9a</RE_ZEILE4><RE_ZEILE5>0811 Musterstadt</RE_ZEILE5><SPERRE_BIS>1899-12-30T00:00:00</SPERRE_BIS><SPERRE_VON>1899-12-30T00:00:00</SPERRE_VON><STARTGROBTERMIN>2025-10-26T00:00:00</STARTGROBTERMIN><STOCK> </STOCK><STORT> </STORT><STORTTXT> </STORTTXT><STRASSE>Muster Weg</STRASSE><VB_LAGEZUSATZ> </VB_LAGEZUSATZ><VB_NOTIZ> </VB_NOTIZ><VB_NUM>175214</VB_NUM><VB_RAUM> </VB_RAUM><VB_STOCK> </VB_STOCK><VB_WOHNUNGSNR>00000013</VB_WOHNUNGSNR><WOHNUNGNR> </WOHNUNGNR><AUF_ID>536145446</AUF_ID>
<ACT> <ALTERG>66965</ALTERG><BEZEICHNER>Zählerstand</BEZEICHNER><DATALTERG>2024-12-31T00:00:00</DATALTERG><ERG></ERG><FAKTOR>1.000000</FAKTOR><FOLGE>19</FOLGE><HOSTKEY>ZM_KLASSEN</HOSTKEY><KENNZIFFER1>1-1:1.8.0</KENNZIFFER1><KLASSE>MECH</KLASSE><KNOPFFOLGE>1</KNOPFFOLGE><KNOPFGRUPPE>AGERAET</KNOPFGRUPPE><KNOPFTEXT>Ausbau  1EBZ0100020423</KNOPFTEXT><MERKMAL>MECH-ZW</MERKMAL><NACHKOMMA>0</NACHKOMMA><OBERGRENZE>0</OBERGRENZE><OBJEKT>1EBZ0100020423</OBJEKT><STELLEN>0</STELLEN><TARIF>1-1:1.8.0</TARIF><TOLERANZMINUS>30</TOLERANZMINUS><TOLERANZPLUS>40</TOLERANZPLUS><UNTERGRENZE>0</UNTERGRENZE><ZWNUMMER></ZWNUMMER><ACT_ID>536145505</ACT_ID>
</ACT>
<ACT> <ALTERG></ALTERG><BEZEICHNER>Address_from</BEZEICHNER><DATALTERG>1899-12-30T00:00:00</DATALTERG><ERG>2022-08-01</ERG><FAKTOR>1.000000</FAKTOR><FOLGE>2</FOLGE><HOSTKEY>ZM_KLASSEN</HOSTKEY><KENNZIFFER1> </KENNZIFFER1><KLASSE>CHECK</KLASSE><KNOPFFOLGE>1</KNOPFFOLGE><KNOPFGRUPPE>INFO</KNOPFGRUPPE><KNOPFTEXT> Heike-Petra Lippert-1</KNOPFTEXT><MERKMAL>CHECK-INFO</MERKMAL><NACHKOMMA>1</NACHKOMMA><OBERGRENZE>0.0</OBERGRENZE><OBJEKT>Anschrift-1</OBJEKT><STELLEN>50</STELLEN><TARIF></TARIF><TOLERANZMINUS>0</TOLERANZMINUS><TOLERANZPLUS>0</TOLERANZPLUS><UNTERGRENZE>0.0</UNTERGRENZE><ZWNUMMER></ZWNUMMER><ACT_ID>536145551</ACT_ID>
</ACT>
<ACT> <ALTERG></ALTERG><BEZEICHNER>Address_id</BEZEICHNER><DATALTERG>1899-12-30T00:00:00</DATALTERG><ERG>3448203</ERG><FAKTOR>1.000000</FAKTOR><FOLGE>1</FOLGE><HOSTKEY>ZM_KLASSEN</HOSTKEY><KENNZIFFER1> </KENNZIFFER1><KLASSE>CHECK</KLASSE><KNOPFFOLGE>1</KNOPFFOLGE><KNOPFGRUPPE>INFO</KNOPFGRUPPE><KNOPFTEXT> Heike-Petra Lippert-1</KNOPFTEXT><MERKMAL>CHECK-INFO</MERKMAL><NACHKOMMA>1</NACHKOMMA><OBERGRENZE>0.0</OBERGRENZE><OBJEKT>Anschrift-1</OBJEKT><STELLEN>50</STELLEN><TARIF></TARIF><TOLERANZMINUS>0</TOLERANZMINUS><TOLERANZPLUS>0</TOLERANZPLUS><UNTERGRENZE>0.0</UNTERGRENZE><ZWNUMMER></ZWNUMMER><ACT_ID>536145550</ACT_ID>
</ACT>
<ACT> <ALTERG></ALTERG><BEZEICHNER>Anlagenklartuntertypbez</BEZEICHNER><DATALTERG>1899-12-30T00:00:00</DATALTERG><ERG>Smartmetergateway</ERG><FAKTOR>1.000000</FAKTOR><FOLGE>1</FOLGE><HOSTKEY>ZM_KLASSEN</HOSTKEY><KENNZIFFER1> </KENNZIFFER1><KLASSE>SMGW</KLASSE><KNOPFFOLGE>2</KNOPFFOLGE><KNOPFGRUPPE>EGERAET</KNOPFGRUPPE><KNOPFTEXT>Einbau SMG </KNOPFTEXT><MERKMAL>SMGW-INFO</MERKMAL><NACHKOMMA>1</NACHKOMMA><OBERGRENZE>0.0</OBERGRENZE><OBJEKT>140726</OBJEKT><STELLEN>50</STELLEN><TARIF></TARIF><TOLERANZMINUS>0</TOLERANZMINUS><TOLERANZPLUS>0</TOLERANZPLUS><UNTERGRENZE>0.0</UNTERGRENZE><ZWNUMMER></ZWNUMMER><ACT_ID>536145532</ACT_ID>
</ACT>
<ACT> <ALTERG></ALTERG><BEZEICHNER>Anlagenklartuntertypkz</BEZEICHNER><DATALTERG>1899-12-30T00:00:00</DATALTERG><ERG>SMG</ERG><FAKTOR>1.000000</FAKTOR><FOLGE>1</FOLGE><HOSTKEY>ZM_KLASSEN</HOSTKEY><KENNZIFFER1> </KENNZIFFER1><KLASSE>SMGW</KLASSE><KNOPFFOLGE>2</KNOPFFOLGE><KNOPFGRUPPE>EGERAET</KNOPFGRUPPE><KNOPFTEXT>Einbau SMG </KNOPFTEXT><MERKMAL>SMGW-INFO</MERKMAL><NACHKOMMA>1</NACHKOMMA><OBERGRENZE>0.0</OBERGRENZE><OBJEKT>140726</OBJEKT><STELLEN>50</STELLEN><TARIF></TARIF><TOLERANZMINUS>0</TOLERANZMINUS><TOLERANZPLUS>0</TOLERANZPLUS><UNTERGRENZE>0.0</UNTERGRENZE><ZWNUMMER></ZWNUMMER><ACT_ID>536145531</ACT_ID>
</ACT>
<ACT> <ALTERG></ALTERG><BEZEICHNER>Anlagenklassenartbez</BEZEICHNER><DATALTERG>1899-12-30T00:00:00</DATALTERG><ERG>Technische Steuereinheit</ERG><FAKTOR>1.000000</FAKTOR><FOLGE>1</FOLGE><HOSTKEY>ZM_KLASSEN</HOSTKEY><KENNZIFFER1> </KENNZIFFER1><KLASSE>SMGW</KLASSE><KNOPFFOLGE>2</KNOPFFOLGE><KNOPFGRUPPE>EGERAET</KNOPFGRUPPE><KNOPFTEXT>Einbau SMG </KNOPFTEXT><MERKMAL>SMGW-INFO</MERKMAL><NACHKOMMA>1</NACHKOMMA><OBERGRENZE>0.0</OBERGRENZE><OBJEKT>140726</OBJEKT><STELLEN>50</STELLEN><TARIF></TARIF><TOLERANZMINUS>0</TOLERANZMINUS><TOLERANZPLUS>0</TOLERANZPLUS><UNTERGRENZE>0.0</UNTERGRENZE><ZWNUMMER></ZWNUMMER><ACT_ID>536145530</ACT_ID>
</ACT>
<ACT> <ALTERG></ALTERG><BEZEICHNER>Anlagenklassenartbez</BEZEICHNER><DATALTERG>1899-12-30T00:00:00</DATALTERG><ERG>Zaehler</ERG><FAKTOR>1.000000</FAKTOR><FOLGE>1</FOLGE><HOSTKEY>ZM_KLASSEN</HOSTKEY><KENNZIFFER1> </KENNZIFFER1><KLASSE>MECH</KLASSE><KNOPFFOLGE>1</KNOPFFOLGE><KNOPFGRUPPE>AGERAET</KNOPFGRUPPE><KNOPFTEXT>Ausbau  1EBZ0100020423</KNOPFTEXT><MERKMAL>MECH-INFO</MERKMAL><NACHKOMMA>0</NACHKOMMA><OBERGRENZE>0</OBERGRENZE><OBJEKT>1EBZ0100020423</OBJEKT><STELLEN>0</STELLEN><TARIF></TARIF><TOLERANZMINUS>0</TOLERANZMINUS><TOLERANZPLUS>0</TOLERANZPLUS><UNTERGRENZE>0</UNTERGRENZE><ZWNUMMER></ZWNUMMER><ACT_ID>536145483</ACT_ID>
</ACT>
<ACT> <ALTERG></ALTERG><BEZEICHNER>Anlagenklassenartkz</BEZEICHNER><DATALTERG>1899-12-30T00:00:00</DATALTERG><ERG>T</ERG><FAKTOR>1.000000</FAKTOR><FOLGE>1</FOLGE><HOSTKEY>ZM_KLASSEN</HOSTKEY><KENNZIFFER1> </KENNZIFFER1><KLASSE>SMGW</KLASSE><KNOPFFOLGE>2</KNOPFFOLGE><KNOPFGRUPPE>EGERAET</KNOPFGRUPPE><KNOPFTEXT>Einbau SMG </KNOPFTEXT><MERKMAL>SMGW-INFO</MERKMAL><NACHKOMMA>1</NACHKOMMA><OBERGRENZE>0.0</OBERGRENZE><OBJEKT>140726</OBJEKT><STELLEN>50</STELLEN><TARIF></TARIF><TOLERANZMINUS>0</TOLERANZMINUS><TOLERANZPLUS>0</TOLERANZPLUS><UNTERGRENZE>0.0</UNTERGRENZE><ZWNUMMER></ZWNUMMER><ACT_ID>536145529</ACT_ID>
</ACT>
<ACT> <ALTERG></ALTERG><BEZEICHNER>Anlagenklassenartkz</BEZEICHNER><DATALTERG>1899-12-30T00:00:00</DATALTERG><ERG>Z</ERG><FAKTOR>1.000000</FAKTOR><FOLGE>1</FOLGE><HOSTKEY>ZM_KLASSEN</HOSTKEY><KENNZIFFER1> </KENNZIFFER1><KLASSE>MECH</KLASSE><KNOPFFOLGE>1</KNOPFFOLGE><KNOPFGRUPPE>AGERAET</KNOPFGRUPPE><KNOPFTEXT>Ausbau  1EBZ0100020423</KNOPFTEXT><MERKMAL>MECH-INFO</MERKMAL><NACHKOMMA>0</NACHKOMMA><OBERGRENZE>0</OBERGRENZE><OBJEKT>1EBZ0100020423</OBJEKT><STELLEN>0</STELLEN><TARIF></TARIF><TOLERANZMINUS>0</TOLERANZMINUS><TOLERANZPLUS>0</TOLERANZPLUS><UNTERGRENZE>0</UNTERGRENZE><ZWNUMMER></ZWNUMMER><ACT_ID>536145482</ACT_ID>
</ACT>
<ACT> <ALTERG></ALTERG><BEZEICHNER>Anlagentypbauart</BEZEICHNER><DATALTERG>1899-12-30T00:00:00</DATALTERG><ERG>mME DS</ERG><FAKTOR>1.000000</FAKTOR><FOLGE>1</FOLGE><HOSTKEY>ZM_KLASSEN</HOSTKEY><KENNZIFFER1> </KENNZIFFER1><KLASSE>MECH</KLASSE><KNOPFFOLGE>1</KNOPFFOLGE><KNOPFGRUPPE>AGERAET</KNOPFGRUPPE><KNOPFTEXT>Ausbau  1EBZ0100020423</KNOPFTEXT><MERKMAL>MECH-INFO</MERKMAL><NACHKOMMA>0</NACHKOMMA><OBERGRENZE>0</OBERGRENZE><OBJEKT>1EBZ0100020423</OBJEKT><STELLEN>0</STELLEN><TARIF></TARIF><TOLERANZMINUS>0</TOLERANZMINUS><TOLERANZPLUS>0</TOLERANZPLUS><UNTERGRENZE>0</UNTERGRENZE><ZWNUMMER></ZWNUMMER><ACT_ID>536145485</ACT_ID>
</ACT>
<ACT> <ALTERG></ALTERG><BEZEICHNER>Anlagentypeinbaulage</BEZEICHNER><DATALTERG>1899-12-30T00:00:00</DATALTERG><ERG>5&#47;60 A</ERG><FAKTOR>1.000000</FAKTOR><FOLGE>1</FOLGE><HOSTKEY>ZM_KLASSEN</HOSTKEY><KENNZIFFER1> </KENNZIFFER1><KLASSE>MECH</KLASSE><KNOPFFOLGE>1</KNOPFFOLGE><KNOPFGRUPPE>AGERAET</KNOPFGRUPPE><KNOPFTEXT>Ausbau  1EBZ0100020423</KNOPFTEXT><MERKMAL>MECH-INFO</MERKMAL><NACHKOMMA>0</NACHKOMMA><OBERGRENZE>0</OBERGRENZE><OBJEKT>1EBZ0100020423</OBJEKT><STELLEN>0</STELLEN><TARIF></TARIF><TOLERANZMINUS>0</TOLERANZMINUS><TOLERANZPLUS>0</TOLERANZPLUS><UNTERGRENZE>0</UNTERGRENZE><ZWNUMMER></ZWNUMMER><ACT_ID>536145486</ACT_ID>
</ACT>
<ACT> <ALTERG></ALTERG><BEZEICHNER>Anlagentypkz</BEZEICHNER><DATALTERG>1899-12-30T00:00:00</DATALTERG><ERG>20161017</ERG><FAKTOR>1.000000</FAKTOR><FOLGE>1</FOLGE><HOSTKEY>ZM_KLASSEN</HOSTKEY><KENNZIFFER1> </KENNZIFFER1><KLASSE>MECH</KLASSE><KNOPFFOLGE>1</KNOPFFOLGE><KNOPFGRUPPE>AGERAET</KNOPFGRUPPE><KNOPFTEXT>Ausbau  1EBZ0100020423</KNOPFTEXT><MERKMAL>MECH-INFO</MERKMAL><NACHKOMMA>0</NACHKOMMA><OBERGRENZE>0</OBERGRENZE><OBJEKT>1EBZ0100020423</OBJEKT><STELLEN>0</STELLEN><TARIF></TARIF><TOLERANZMINUS>0</TOLERANZMINUS><TOLERANZPLUS>0</TOLERANZPLUS><UNTERGRENZE>0</UNTERGRENZE><ZWNUMMER></ZWNUMMER><ACT_ID>536145484</ACT_ID>
</ACT>
<ACT> <ALTERG></ALTERG><BEZEICHNER>AO: Hinweis</BEZEICHNER><DATALTERG>1899-12-30T00:00:00</DATALTERG><ERG> Anschlussraum, Restaurant</ERG><FAKTOR>1.000000</FAKTOR><FOLGE>20</FOLGE><HOSTKEY>ZM_AO_HINWEIS</HOSTKEY><KENNZIFFER1> </KENNZIFFER1><KLASSE></KLASSE><KNOPFFOLGE></KNOPFFOLGE><KNOPFGRUPPE></KNOPFGRUPPE><KNOPFTEXT></KNOPFTEXT><MERKMAL></MERKMAL><NACHKOMMA>0</NACHKOMMA><OBERGRENZE>0</OBERGRENZE><OBJEKT></OBJEKT><STELLEN>0</STELLEN><TARIF></TARIF><TOLERANZMINUS>0</TOLERANZMINUS><TOLERANZPLUS>0</TOLERANZPLUS><UNTERGRENZE>0</UNTERGRENZE><ZWNUMMER></ZWNUMMER><ACT_ID>536145447</ACT_ID>
</ACT>
<ACT> <ALTERG></ALTERG><BEZEICHNER>AO: Hinweis NEU</BEZEICHNER><DATALTERG>1899-12-30T00:00:00</DATALTERG><ERG></ERG><FAKTOR>1.000000</FAKTOR><FOLGE>21</FOLGE><HOSTKEY>ZM_AO_HINWEIS_NEU</HOSTKEY><KENNZIFFER1> </KENNZIFFER1><KLASSE></KLASSE><KNOPFFOLGE></KNOPFFOLGE><KNOPFGRUPPE></KNOPFGRUPPE><KNOPFTEXT></KNOPFTEXT><MERKMAL></MERKMAL><NACHKOMMA>0</NACHKOMMA><OBERGRENZE>0</OBERGRENZE><OBJEKT></OBJEKT><STELLEN>0</STELLEN><TARIF></TARIF><TOLERANZMINUS>0</TOLERANZMINUS><TOLERANZPLUS>0</TOLERANZPLUS><UNTERGRENZE>0</UNTERGRENZE><ZWNUMMER></ZWNUMMER><ACT_ID>536145449</ACT_ID>
</ACT>
<ACT> <ALTERG></ALTERG><BEZEICHNER>BK_QUALI</BEZEICHNER><DATALTERG>1899-12-30T00:00:00</DATALTERG><ERG>QUALI</ERG><FAKTOR>1.000000</FAKTOR><FOLGE>1</FOLGE><HOSTKEY>ZM_KLASSEN</HOSTKEY><KENNZIFFER1> </KENNZIFFER1><KLASSE>MECH</KLASSE><KNOPFFOLGE>1</KNOPFFOLGE><KNOPFGRUPPE>AGERAET</KNOPFGRUPPE><KNOPFTEXT>Ausbau  1EBZ0100020423</KNOPFTEXT><MERKMAL>MECH-INFO</MERKMAL><NACHKOMMA>0</NACHKOMMA><OBERGRENZE>0</OBERGRENZE><OBJEKT>1EBZ0100020423</OBJEKT><STELLEN>0</STELLEN><TARIF></TARIF><TOLERANZMINUS>0</TOLERANZMINUS><TOLERANZPLUS>0</TOLERANZPLUS><UNTERGRENZE>0</UNTERGRENZE><ZWNUMMER></ZWNUMMER><ACT_ID>536145494</ACT_ID>
</ACT>
<ACT> <ALTERG></ALTERG><BEZEICHNER>BK_QUALI</BEZEICHNER><DATALTERG>1899-12-30T00:00:00</DATALTERG><ERG>QUALI</ERG><FAKTOR>1.000000</FAKTOR><FOLGE>1</FOLGE><HOSTKEY>ZM_KLASSEN</HOSTKEY><KENNZIFFER1> </KENNZIFFER1><KLASSE>SMGW</KLASSE><KNOPFFOLGE>2</KNOPFFOLGE><KNOPFGRUPPE>EGERAET</KNOPFGRUPPE><KNOPFTEXT>Einbau SMG </KNOPFTEXT><MERKMAL>SMGW-INFO</MERKMAL><NACHKOMMA>1</NACHKOMMA><OBERGRENZE>0.0</OBERGRENZE><OBJEKT>140726</OBJEKT><STELLEN>50</STELLEN><TARIF></TARIF><TOLERANZMINUS>0</TOLERANZMINUS><TOLERANZPLUS>0</TOLERANZPLUS><UNTERGRENZE>0.0</UNTERGRENZE><ZWNUMMER></ZWNUMMER><ACT_ID>536145536</ACT_ID>
</ACT>
<ACT> <ALTERG></ALTERG><BEZEICHNER>BK_TREIBER</BEZEICHNER><DATALTERG>1899-12-30T00:00:00</DATALTERG><ERG>MECH</ERG><FAKTOR>1.000000</FAKTOR><FOLGE>1</FOLGE><HOSTKEY>ZM_KLASSEN</HOSTKEY><KENNZIFFER1> </KENNZIFFER1><KLASSE>MECH</KLASSE><KNOPFFOLGE>1</KNOPFFOLGE><KNOPFGRUPPE>AGERAET</KNOPFGRUPPE><KNOPFTEXT>Ausbau  1EBZ0100020423</KNOPFTEXT><MERKMAL>MECH-INFO</MERKMAL><NACHKOMMA>0</NACHKOMMA><OBERGRENZE>0</OBERGRENZE><OBJEKT>1EBZ0100020423</OBJEKT><STELLEN>0</STELLEN><TARIF></TARIF><TOLERANZMINUS>0</TOLERANZMINUS><TOLERANZPLUS>0</TOLERANZPLUS><UNTERGRENZE>0</UNTERGRENZE><ZWNUMMER></ZWNUMMER><ACT_ID>536145496</ACT_ID>
</ACT>
<ACT> <ALTERG></ALTERG><BEZEICHNER>BK_TREIBER</BEZEICHNER><DATALTERG>1899-12-30T00:00:00</DATALTERG><ERG>SMGW</ERG><FAKTOR>1.000000</FAKTOR><FOLGE>1</FOLGE><HOSTKEY>ZM_KLASSEN</HOSTKEY><KENNZIFFER1> </KENNZIFFER1><KLASSE>SMGW</KLASSE><KNOPFFOLGE>2</KNOPFFOLGE><KNOPFGRUPPE>EGERAET</KNOPFGRUPPE><KNOPFTEXT>Einbau SMG </KNOPFTEXT><MERKMAL>SMGW-INFO</MERKMAL><NACHKOMMA>1</NACHKOMMA><OBERGRENZE>0.0</OBERGRENZE><OBJEKT>140726</OBJEKT><STELLEN>50</STELLEN><TARIF></TARIF><TOLERANZMINUS>0</TOLERANZMINUS><TOLERANZPLUS>0</TOLERANZPLUS><UNTERGRENZE>0.0</UNTERGRENZE><ZWNUMMER></ZWNUMMER><ACT_ID>536145537</ACT_ID>
</ACT>
<ACT> <ALTERG></ALTERG><BEZEICHNER>BK_ZEIT</BEZEICHNER><DATALTERG>1899-12-30T00:00:00</DATALTERG><ERG>12</ERG><FAKTOR>1.000000</FAKTOR><FOLGE>1</FOLGE><HOSTKEY>ZM_KLASSEN</HOSTKEY><KENNZIFFER1> </KENNZIFFER1><KLASSE>SMGW</KLASSE><KNOPFFOLGE>2</KNOPFFOLGE><KNOPFGRUPPE>EGERAET</KNOPFGRUPPE><KNOPFTEXT>Einbau SMG </KNOPFTEXT><MERKMAL>SMGW-INFO</MERKMAL><NACHKOMMA>1</NACHKOMMA><OBERGRENZE>0.0</OBERGRENZE><OBJEKT>140726</OBJEKT><STELLEN>50</STELLEN><TARIF></TARIF><TOLERANZMINUS>0</TOLERANZMINUS><TOLERANZPLUS>0</TOLERANZPLUS><UNTERGRENZE>0.0</UNTERGRENZE><ZWNUMMER></ZWNUMMER><ACT_ID>536145535</ACT_ID>
</ACT>
<ACT> <ALTERG></ALTERG><BEZEICHNER>BK_ZEIT</BEZEICHNER><DATALTERG>1899-12-30T00:00:00</DATALTERG><ERG>30</ERG><FAKTOR>1.000000</FAKTOR><FOLGE>1</FOLGE><HOSTKEY>ZM_KLASSEN</HOSTKEY><KENNZIFFER1> </KENNZIFFER1><KLASSE>MECH</KLASSE><KNOPFFOLGE>1</KNOPFFOLGE><KNOPFGRUPPE>AGERAET</KNOPFGRUPPE><KNOPFTEXT>Ausbau  1EBZ0100020423</KNOPFTEXT><MERKMAL>MECH-INFO</MERKMAL><NACHKOMMA>0</NACHKOMMA><OBERGRENZE>0</OBERGRENZE><OBJEKT>1EBZ0100020423</OBJEKT><STELLEN>0</STELLEN><TARIF></TARIF><TOLERANZMINUS>0</TOLERANZMINUS><TOLERANZPLUS>0</TOLERANZPLUS><UNTERGRENZE>0</UNTERGRENZE><ZWNUMMER></ZWNUMMER><ACT_ID>536145495</ACT_ID>
</ACT>
<ACT> <ALTERG></ALTERG><BEZEICHNER>City</BEZEICHNER><DATALTERG>1899-12-30T00:00:00</DATALTERG><ERG>Hillerse</ERG><FAKTOR>1.000000</FAKTOR><FOLGE>6</FOLGE><HOSTKEY>ZM_KLASSEN</HOSTKEY><KENNZIFFER1> </KENNZIFFER1><KLASSE>CHECK</KLASSE><KNOPFFOLGE>1</KNOPFFOLGE><KNOPFGRUPPE>INFO</KNOPFGRUPPE><KNOPFTEXT> Heike-Petra Lippert-1</KNOPFTEXT><MERKMAL>CHECK-INFO</MERKMAL><NACHKOMMA>1</NACHKOMMA><OBERGRENZE>0.0</OBERGRENZE><OBJEKT>Anschrift-1</OBJEKT><STELLEN>50</STELLEN><TARIF></TARIF><TOLERANZMINUS>0</TOLERANZMINUS><TOLERANZPLUS>0</TOLERANZPLUS><UNTERGRENZE>0.0</UNTERGRENZE><ZWNUMMER></ZWNUMMER><ACT_ID>536145555</ACT_ID>
</ACT>
<ACT> <ALTERG></ALTERG><BEZEICHNER>Country_code</BEZEICHNER><DATALTERG>1899-12-30T00:00:00</DATALTERG><ERG>DE</ERG><FAKTOR>1.000000</FAKTOR><FOLGE>5</FOLGE><HOSTKEY>ZM_KLASSEN</HOSTKEY><KENNZIFFER1> </KENNZIFFER1><KLASSE>CHECK</KLASSE><KNOPFFOLGE>1</KNOPFFOLGE><KNOPFGRUPPE>INFO</KNOPFGRUPPE><KNOPFTEXT> Heike-Petra Lippert-1</KNOPFTEXT><MERKMAL>CHECK-INFO</MERKMAL><NACHKOMMA>1</NACHKOMMA><OBERGRENZE>0.0</OBERGRENZE><OBJEKT>Anschrift-1</OBJEKT><STELLEN>50</STELLEN><TARIF></TARIF><TOLERANZMINUS>0</TOLERANZMINUS><TOLERANZPLUS>0</TOLERANZPLUS><UNTERGRENZE>0.0</UNTERGRENZE><ZWNUMMER></ZWNUMMER><ACT_ID>536145554</ACT_ID>
</ACT>
<ACT> <ALTERG></ALTERG><BEZEICHNER>Datum Ablauf Eichung</BEZEICHNER><DATALTERG>1899-12-30T00:00:00</DATALTERG><ERG>2025</ERG><FAKTOR>1.000000</FAKTOR><FOLGE>3</FOLGE><HOSTKEY>ZM_KLASSEN</HOSTKEY><KENNZIFFER1> </KENNZIFFER1><KLASSE>MECH</KLASSE><KNOPFFOLGE>1</KNOPFFOLGE><KNOPFGRUPPE>AGERAET</KNOPFGRUPPE><KNOPFTEXT>Ausbau  1EBZ0100020423</KNOPFTEXT><MERKMAL>MECH-INFO</MERKMAL><NACHKOMMA>0</NACHKOMMA><OBERGRENZE>0</OBERGRENZE><OBJEKT>1EBZ0100020423</OBJEKT><STELLEN>0</STELLEN><TARIF></TARIF><TOLERANZMINUS>0</TOLERANZMINUS><TOLERANZPLUS>0</TOLERANZPLUS><UNTERGRENZE>0</UNTERGRENZE><ZWNUMMER></ZWNUMMER><ACT_ID>536145498</ACT_ID>
</ACT>
<ACT> <ALTERG></ALTERG><BEZEICHNER>Datum der Eichung</BEZEICHNER><DATALTERG>1899-12-30T00:00:00</DATALTERG><ERG>2017</ERG><FAKTOR>1.000000</FAKTOR><FOLGE>2</FOLGE><HOSTKEY>ZM_KLASSEN</HOSTKEY><KENNZIFFER1> </KENNZIFFER1><KLASSE>MECH</KLASSE><KNOPFFOLGE>1</KNOPFFOLGE><KNOPFGRUPPE>AGERAET</KNOPFGRUPPE><KNOPFTEXT>Ausbau  1EBZ0100020423</KNOPFTEXT><MERKMAL>MECH-INFO</MERKMAL><NACHKOMMA>0</NACHKOMMA><OBERGRENZE>0</OBERGRENZE><OBJEKT>1EBZ0100020423</OBJEKT><STELLEN>0</STELLEN><TARIF></TARIF><TOLERANZMINUS>0</TOLERANZMINUS><TOLERANZPLUS>0</TOLERANZPLUS><UNTERGRENZE>0</UNTERGRENZE><ZWNUMMER></ZWNUMMER><ACT_ID>536145497</ACT_ID>
</ACT>
<ACT> <ALTERG></ALTERG><BEZEICHNER>Energieartkz</BEZEICHNER><DATALTERG>1899-12-30T00:00:00</DATALTERG><ERG>E</ERG><FAKTOR>1.000000</FAKTOR><FOLGE>1</FOLGE><HOSTKEY>ZM_KLASSEN</HOSTKEY><KENNZIFFER1> </KENNZIFFER1><KLASSE>MECH</KLASSE><KNOPFFOLGE>1</KNOPFFOLGE><KNOPFGRUPPE>AGERAET</KNOPFGRUPPE><KNOPFTEXT>Ausbau  1EBZ0100020423</KNOPFTEXT><MERKMAL>MECH-INFO</MERKMAL><NACHKOMMA>0</NACHKOMMA><OBERGRENZE>0</OBERGRENZE><OBJEKT>1EBZ0100020423</OBJEKT><STELLEN>0</STELLEN><TARIF></TARIF><TOLERANZMINUS>0</TOLERANZMINUS><TOLERANZPLUS>0</TOLERANZPLUS><UNTERGRENZE>0</UNTERGRENZE><ZWNUMMER></ZWNUMMER><ACT_ID>536145487</ACT_ID>
</ACT>
<ACT> <ALTERG></ALTERG><BEZEICHNER>Energieartkz</BEZEICHNER><DATALTERG>1899-12-30T00:00:00</DATALTERG><ERG>S</ERG><FAKTOR>1.000000</FAKTOR><FOLGE>1</FOLGE><HOSTKEY>ZM_KLASSEN</HOSTKEY><KENNZIFFER1> </KENNZIFFER1><KLASSE>SMGW</KLASSE><KNOPFFOLGE>2</KNOPFFOLGE><KNOPFGRUPPE>EGERAET</KNOPFGRUPPE><KNOPFTEXT>Einbau SMG </KNOPFTEXT><MERKMAL>SMGW-INFO</MERKMAL><NACHKOMMA>1</NACHKOMMA><OBERGRENZE>0.0</OBERGRENZE><OBJEKT>140726</OBJEKT><STELLEN>50</STELLEN><TARIF></TARIF><TOLERANZMINUS>0</TOLERANZMINUS><TOLERANZPLUS>0</TOLERANZPLUS><UNTERGRENZE>0.0</UNTERGRENZE><ZWNUMMER></ZWNUMMER><ACT_ID>536145533</ACT_ID>
</ACT>
<ACT> <ALTERG></ALTERG><BEZEICHNER>Externe Losbezeichung</BEZEICHNER><DATALTERG>1899-12-30T00:00:00</DATALTERG><ERG>E-25-01</ERG><FAKTOR>1.000000</FAKTOR><FOLGE>3</FOLGE><HOSTKEY>ZM_KLASSEN</HOSTKEY><KENNZIFFER1> </KENNZIFFER1><KLASSE>MECH</KLASSE><KNOPFFOLGE>1</KNOPFFOLGE><KNOPFGRUPPE>AGERAET</KNOPFGRUPPE><KNOPFTEXT>Ausbau  1EBZ0100020423</KNOPFTEXT><MERKMAL>MECH-INFO</MERKMAL><NACHKOMMA>0</NACHKOMMA><OBERGRENZE>0</OBERGRENZE><OBJEKT>1EBZ0100020423</OBJEKT><STELLEN>0</STELLEN><TARIF></TARIF><TOLERANZMINUS>0</TOLERANZMINUS><TOLERANZPLUS>0</TOLERANZPLUS><UNTERGRENZE>0</UNTERGRENZE><ZWNUMMER></ZWNUMMER><ACT_ID>536145500</ACT_ID>
</ACT>
<ACT> <ALTERG></ALTERG><BEZEICHNER>FDL Auftragshistorie</BEZEICHNER><DATALTERG>1899-12-30T00:00:00</DATALTERG><ERG></ERG><FAKTOR>1.000000</FAKTOR><FOLGE>26</FOLGE><HOSTKEY>ZM_FDL_HIST</HOSTKEY><KENNZIFFER1> </KENNZIFFER1><KLASSE></KLASSE><KNOPFFOLGE></KNOPFFOLGE><KNOPFGRUPPE></KNOPFGRUPPE><KNOPFTEXT></KNOPFTEXT><MERKMAL></MERKMAL><NACHKOMMA>0</NACHKOMMA><OBERGRENZE>0</OBERGRENZE><OBJEKT></OBJEKT><STELLEN>0</STELLEN><TARIF></TARIF><TOLERANZMINUS>0</TOLERANZMINUS><TOLERANZPLUS>0</TOLERANZPLUS><UNTERGRENZE>0</UNTERGRENZE><ZWNUMMER></ZWNUMMER><ACT_ID>536145569</ACT_ID>
</ACT>
<ACT> <ALTERG></ALTERG><BEZEICHNER>Foto</BEZEICHNER><DATALTERG>1899-12-30T00:00:00</DATALTERG><ERG></ERG><FAKTOR>1.000000</FAKTOR><FOLGE>2</FOLGE><HOSTKEY>SMGW-FOTO</HOSTKEY><KENNZIFFER1> </KENNZIFFER1><KLASSE>SMGW</KLASSE><KNOPFFOLGE>2</KNOPFFOLGE><KNOPFGRUPPE>EGERAET</KNOPFGRUPPE><KNOPFTEXT>Einbau SMG </KNOPFTEXT><MERKMAL>SMGW-FOTO</MERKMAL><NACHKOMMA>1</NACHKOMMA><OBERGRENZE>0.0</OBERGRENZE><OBJEKT>140726</OBJEKT><STELLEN>0</STELLEN><TARIF></TARIF><TOLERANZMINUS>0</TOLERANZMINUS><TOLERANZPLUS>0</TOLERANZPLUS><UNTERGRENZE>0.0</UNTERGRENZE><ZWNUMMER></ZWNUMMER><ACT_ID>536145573</ACT_ID>
</ACT>
<ACT> <ALTERG></ALTERG><BEZEICHNER>Foto</BEZEICHNER><DATALTERG>1899-12-30T00:00:00</DATALTERG><ERG></ERG><FAKTOR>1.000000</FAKTOR><FOLGE>2</FOLGE><HOSTKEY>SMGW-FOTO</HOSTKEY><KENNZIFFER1> </KENNZIFFER1><KLASSE>SMGW</KLASSE><KNOPFFOLGE>4</KNOPFFOLGE><KNOPFGRUPPE>ZUSATZGERAET</KNOPFGRUPPE><KNOPFTEXT>Verbindung SMWG - mMe</KNOPFTEXT><MERKMAL>SMGW-FOTO</MERKMAL><NACHKOMMA>1</NACHKOMMA><OBERGRENZE>0.0</OBERGRENZE><OBJEKT>140727</OBJEKT><STELLEN>0</STELLEN><TARIF></TARIF><TOLERANZMINUS>0</TOLERANZMINUS><TOLERANZPLUS>0</TOLERANZPLUS><UNTERGRENZE>0.0</UNTERGRENZE><ZWNUMMER></ZWNUMMER><ACT_ID>536145574</ACT_ID>
</ACT>
<ACT> <ALTERG></ALTERG><BEZEICHNER>Foto</BEZEICHNER><DATALTERG>1899-12-30T00:00:00</DATALTERG><ERG></ERG><FAKTOR>1.000000</FAKTOR><FOLGE>9</FOLGE><HOSTKEY>ZM_FOTO</HOSTKEY><KENNZIFFER1> </KENNZIFFER1><KLASSE></KLASSE><KNOPFFOLGE></KNOPFFOLGE><KNOPFGRUPPE></KNOPFGRUPPE><KNOPFTEXT></KNOPFTEXT><MERKMAL></MERKMAL><NACHKOMMA>1</NACHKOMMA><OBERGRENZE>0.0</OBERGRENZE><OBJEKT></OBJEKT><STELLEN>50</STELLEN><TARIF></TARIF><TOLERANZMINUS>0</TOLERANZMINUS><TOLERANZPLUS>0</TOLERANZPLUS><UNTERGRENZE>0.0</UNTERGRENZE><ZWNUMMER></ZWNUMMER><ACT_ID>536145566</ACT_ID>
</ACT>
<ACT> <ALTERG></ALTERG><BEZEICHNER>FOTO-1-1:1.8.0</BEZEICHNER><DATALTERG>1899-12-30T00:00:00</DATALTERG><ERG></ERG><FAKTOR>1.000000</FAKTOR><FOLGE>4</FOLGE><HOSTKEY>ZM_KLASSEN</HOSTKEY><KENNZIFFER1>1-1:1.8.0</KENNZIFFER1><KLASSE>MECH</KLASSE><KNOPFFOLGE>1</KNOPFFOLGE><KNOPFGRUPPE>AGERAET</KNOPFGRUPPE><KNOPFTEXT>Ausbau  1EBZ0100020423</KNOPFTEXT><MERKMAL>MECH-FOTO</MERKMAL><NACHKOMMA>1</NACHKOMMA><OBERGRENZE>0.0</OBERGRENZE><OBJEKT>1EBZ0100020423</OBJEKT><STELLEN>0</STELLEN><TARIF></TARIF><TOLERANZMINUS>0</TOLERANZMINUS><TOLERANZPLUS>0</TOLERANZPLUS><UNTERGRENZE>0.0</UNTERGRENZE><ZWNUMMER>1</ZWNUMMER><ACT_ID>536145508</ACT_ID>
</ACT>
<ACT> <ALTERG></ALTERG><BEZEICHNER>FOTO-1-1:1.8.0</BEZEICHNER><DATALTERG>1899-12-30T00:00:00</DATALTERG><ERG></ERG><FAKTOR>1.000000</FAKTOR><FOLGE>4</FOLGE><HOSTKEY>ZM_KLASSEN</HOSTKEY><KENNZIFFER1>1-1:1.8.0</KENNZIFFER1><KLASSE>MECH</KLASSE><KNOPFFOLGE>1</KNOPFFOLGE><KNOPFGRUPPE>EGERAET</KNOPFGRUPPE><KNOPFTEXT>Einbau </KNOPFTEXT><MERKMAL>MECH-FOTO</MERKMAL><NACHKOMMA>1</NACHKOMMA><OBERGRENZE>0.0</OBERGRENZE><OBJEKT>140728-EB</OBJEKT><STELLEN>0</STELLEN><TARIF></TARIF><TOLERANZMINUS>0</TOLERANZMINUS><TOLERANZPLUS>0</TOLERANZPLUS><UNTERGRENZE>0.0</UNTERGRENZE><ZWNUMMER>1</ZWNUMMER><ACT_ID>536145519</ACT_ID>
</ACT>
<ACT> <ALTERG></ALTERG><BEZEICHNER>FOTO-1-1:1.8.1</BEZEICHNER><DATALTERG>1899-12-30T00:00:00</DATALTERG><ERG></ERG><FAKTOR>1.000000</FAKTOR><FOLGE>4</FOLGE><HOSTKEY>ZM_KLASSEN</HOSTKEY><KENNZIFFER1>1-1:1.8.1</KENNZIFFER1><KLASSE>MECH</KLASSE><KNOPFFOLGE>1</KNOPFFOLGE><KNOPFGRUPPE>EGERAET</KNOPFGRUPPE><KNOPFTEXT>Einbau </KNOPFTEXT><MERKMAL>MECH-FOTO</MERKMAL><NACHKOMMA>1</NACHKOMMA><OBERGRENZE>0.0</OBERGRENZE><OBJEKT>140728-EB</OBJEKT><STELLEN>0</STELLEN><TARIF></TARIF><TOLERANZMINUS>0</TOLERANZMINUS><TOLERANZPLUS>0</TOLERANZPLUS><UNTERGRENZE>0.0</UNTERGRENZE><ZWNUMMER>2</ZWNUMMER><ACT_ID>536145521</ACT_ID>
</ACT>
<ACT> <ALTERG></ALTERG><BEZEICHNER>FOTO-1-1:1.8.2</BEZEICHNER><DATALTERG>1899-12-30T00:00:00</DATALTERG><ERG></ERG><FAKTOR>1.000000</FAKTOR><FOLGE>4</FOLGE><HOSTKEY>ZM_KLASSEN</HOSTKEY><KENNZIFFER1>1-1:1.8.2</KENNZIFFER1><KLASSE>MECH</KLASSE><KNOPFFOLGE>1</KNOPFFOLGE><KNOPFGRUPPE>EGERAET</KNOPFGRUPPE><KNOPFTEXT>Einbau </KNOPFTEXT><MERKMAL>MECH-FOTO</MERKMAL><NACHKOMMA>1</NACHKOMMA><OBERGRENZE>0.0</OBERGRENZE><OBJEKT>140728-EB</OBJEKT><STELLEN>0</STELLEN><TARIF></TARIF><TOLERANZMINUS>0</TOLERANZMINUS><TOLERANZPLUS>0</TOLERANZPLUS><UNTERGRENZE>0.0</UNTERGRENZE><ZWNUMMER>3</ZWNUMMER><ACT_ID>536145523</ACT_ID>
</ACT>
<ACT> <ALTERG></ALTERG><BEZEICHNER>FOTO-1-1:2.8.0</BEZEICHNER><DATALTERG>1899-12-30T00:00:00</DATALTERG><ERG></ERG><FAKTOR>1.000000</FAKTOR><FOLGE>4</FOLGE><HOSTKEY>ZM_KLASSEN</HOSTKEY><KENNZIFFER1>1-1:2.8.0</KENNZIFFER1><KLASSE>MECH</KLASSE><KNOPFFOLGE>1</KNOPFFOLGE><KNOPFGRUPPE>EGERAET</KNOPFGRUPPE><KNOPFTEXT>Einbau </KNOPFTEXT><MERKMAL>MECH-FOTO</MERKMAL><NACHKOMMA>1</NACHKOMMA><OBERGRENZE>0.0</OBERGRENZE><OBJEKT>140728-EB</OBJEKT><STELLEN>0</STELLEN><TARIF></TARIF><TOLERANZMINUS>0</TOLERANZMINUS><TOLERANZPLUS>0</TOLERANZPLUS><UNTERGRENZE>0.0</UNTERGRENZE><ZWNUMMER>4</ZWNUMMER><ACT_ID>536145525</ACT_ID>
</ACT>
<ACT> <ALTERG></ALTERG><BEZEICHNER>Geraetbaujahr</BEZEICHNER><DATALTERG>1899-12-30T00:00:00</DATALTERG><ERG>2017</ERG><FAKTOR>1.000000</FAKTOR><FOLGE>1</FOLGE><HOSTKEY>ZM_KLASSEN</HOSTKEY><KENNZIFFER1> </KENNZIFFER1><KLASSE>MECH</KLASSE><KNOPFFOLGE>1</KNOPFFOLGE><KNOPFGRUPPE>AGERAET</KNOPFGRUPPE><KNOPFTEXT>Ausbau  1EBZ0100020423</KNOPFTEXT><MERKMAL>MECH-INFO</MERKMAL><NACHKOMMA>0</NACHKOMMA><OBERGRENZE>0</OBERGRENZE><OBJEKT>1EBZ0100020423</OBJEKT><STELLEN>0</STELLEN><TARIF></TARIF><TOLERANZMINUS>0</TOLERANZMINUS><TOLERANZPLUS>0</TOLERANZPLUS><UNTERGRENZE>0</UNTERGRENZE><ZWNUMMER></ZWNUMMER><ACT_ID>536145488</ACT_ID>
</ACT>
<ACT> <ALTERG></ALTERG><BEZEICHNER>geraet_pin</BEZEICHNER><DATALTERG>1899-12-30T00:00:00</DATALTERG><ERG>4151</ERG><FAKTOR>1.000000</FAKTOR><FOLGE>1</FOLGE><HOSTKEY>ZM_KLASSEN</HOSTKEY><KENNZIFFER1> </KENNZIFFER1><KLASSE>MECH</KLASSE><KNOPFFOLGE>1</KNOPFFOLGE><KNOPFGRUPPE>AGERAET</KNOPFGRUPPE><KNOPFTEXT>Ausbau  1EBZ0100020423</KNOPFTEXT><MERKMAL>MECH-INFO</MERKMAL><NACHKOMMA>0</NACHKOMMA><OBERGRENZE>0</OBERGRENZE><OBJEKT>1EBZ0100020423</OBJEKT><STELLEN>0</STELLEN><TARIF></TARIF><TOLERANZMINUS>0</TOLERANZMINUS><TOLERANZPLUS>0</TOLERANZPLUS><UNTERGRENZE>0</UNTERGRENZE><ZWNUMMER></ZWNUMMER><ACT_ID>536145503</ACT_ID>
</ACT>
<ACT> <ALTERG></ALTERG><BEZEICHNER>geraet_pin</BEZEICHNER><DATALTERG>1899-12-30T00:00:00</DATALTERG><ERG>4151</ERG><FAKTOR>1.000000</FAKTOR><FOLGE>1</FOLGE><HOSTKEY>ZM_KLASSEN</HOSTKEY><KENNZIFFER1> </KENNZIFFER1><KLASSE>MECH</KLASSE><KNOPFFOLGE>1</KNOPFFOLGE><KNOPFGRUPPE>EGERAET</KNOPFGRUPPE><KNOPFTEXT>Einbau </KNOPFTEXT><MERKMAL>MECH-INFO</MERKMAL><NACHKOMMA>0</NACHKOMMA><OBERGRENZE>0</OBERGRENZE><OBJEKT>140728-EB</OBJEKT><STELLEN>0</STELLEN><TARIF></TARIF><TOLERANZMINUS>0</TOLERANZMINUS><TOLERANZPLUS>0</TOLERANZPLUS><UNTERGRENZE>0</UNTERGRENZE><ZWNUMMER></ZWNUMMER><ACT_ID>536145516</ACT_ID>
</ACT>
<ACT> <ALTERG></ALTERG><BEZEICHNER>geraet_pin</BEZEICHNER><DATALTERG>1899-12-30T00:00:00</DATALTERG><ERG></ERG><FAKTOR>1.000000</FAKTOR><FOLGE>1</FOLGE><HOSTKEY>ZM_KLASSEN</HOSTKEY><KENNZIFFER1> </KENNZIFFER1><KLASSE>SMGW</KLASSE><KNOPFFOLGE>2</KNOPFFOLGE><KNOPFGRUPPE>EGERAET</KNOPFGRUPPE><KNOPFTEXT>Einbau SMG </KNOPFTEXT><MERKMAL>SMGW-INFO</MERKMAL><NACHKOMMA>1</NACHKOMMA><OBERGRENZE>0.0</OBERGRENZE><OBJEKT>140726</OBJEKT><STELLEN>50</STELLEN><TARIF></TARIF><TOLERANZMINUS>0</TOLERANZMINUS><TOLERANZPLUS>0</TOLERANZPLUS><UNTERGRENZE>0.0</UNTERGRENZE><ZWNUMMER></ZWNUMMER><ACT_ID>536145542</ACT_ID>
</ACT>
<ACT> <ALTERG></ALTERG><BEZEICHNER>Gerät Ablesehinweis</BEZEICHNER><DATALTERG>1899-12-30T00:00:00</DATALTERG><ERG>Anschlussraum, Restaurant</ERG><FAKTOR>1.000000</FAKTOR><FOLGE>1</FOLGE><HOSTKEY>ZM_KLASSEN</HOSTKEY><KENNZIFFER1> </KENNZIFFER1><KLASSE>MECH</KLASSE><KNOPFFOLGE>1</KNOPFFOLGE><KNOPFGRUPPE>EGERAET</KNOPFGRUPPE><KNOPFTEXT>Einbau </KNOPFTEXT><MERKMAL>MECH-STRINGGROSS</MERKMAL><NACHKOMMA>1</NACHKOMMA><OBERGRENZE>0.0</OBERGRENZE><OBJEKT>140728-EB</OBJEKT><STELLEN>200</STELLEN><TARIF></TARIF><TOLERANZMINUS>0</TOLERANZMINUS><TOLERANZPLUS>0</TOLERANZPLUS><UNTERGRENZE>0.0</UNTERGRENZE><ZWNUMMER></ZWNUMMER><ACT_ID>536145514</ACT_ID>
</ACT>
<ACT> <ALTERG></ALTERG><BEZEICHNER>Gerät Ablesehinweis</BEZEICHNER><DATALTERG>1899-12-30T00:00:00</DATALTERG><ERG></ERG><FAKTOR>1.000000</FAKTOR><FOLGE>1</FOLGE><HOSTKEY>ZM_KLASSEN</HOSTKEY><KENNZIFFER1> </KENNZIFFER1><KLASSE>SMGW</KLASSE><KNOPFFOLGE>2</KNOPFFOLGE><KNOPFGRUPPE>EGERAET</KNOPFGRUPPE><KNOPFTEXT>Einbau SMG </KNOPFTEXT><MERKMAL>SMGW-STRINGGROSS</MERKMAL><NACHKOMMA>1</NACHKOMMA><OBERGRENZE>0.0</OBERGRENZE><OBJEKT>140726</OBJEKT><STELLEN>200</STELLEN><TARIF></TARIF><TOLERANZMINUS>0</TOLERANZMINUS><TOLERANZPLUS>0</TOLERANZPLUS><UNTERGRENZE>0.0</UNTERGRENZE><ZWNUMMER></ZWNUMMER><ACT_ID>536145540</ACT_ID>
</ACT>
<ACT> <ALTERG></ALTERG><BEZEICHNER>Gerät Bemerkung</BEZEICHNER><DATALTERG>1899-12-30T00:00:00</DATALTERG><ERG></ERG><FAKTOR>1.000000</FAKTOR><FOLGE>1</FOLGE><HOSTKEY>ZM_KLASSEN</HOSTKEY><KENNZIFFER1> </KENNZIFFER1><KLASSE>MECH</KLASSE><KNOPFFOLGE>1</KNOPFFOLGE><KNOPFGRUPPE>EGERAET</KNOPFGRUPPE><KNOPFTEXT>Einbau </KNOPFTEXT><MERKMAL>MECH-STRINGGROSS</MERKMAL><NACHKOMMA>1</NACHKOMMA><OBERGRENZE>0.0</OBERGRENZE><OBJEKT>140728-EB</OBJEKT><STELLEN>200</STELLEN><TARIF></TARIF><TOLERANZMINUS>0</TOLERANZMINUS><TOLERANZPLUS>0</TOLERANZPLUS><UNTERGRENZE>0.0</UNTERGRENZE><ZWNUMMER></ZWNUMMER><ACT_ID>536145513</ACT_ID>
</ACT>
<ACT> <ALTERG></ALTERG><BEZEICHNER>Gerät Bemerkung</BEZEICHNER><DATALTERG>1899-12-30T00:00:00</DATALTERG><ERG></ERG><FAKTOR>1.000000</FAKTOR><FOLGE>1</FOLGE><HOSTKEY>ZM_KLASSEN</HOSTKEY><KENNZIFFER1> </KENNZIFFER1><KLASSE>SMGW</KLASSE><KNOPFFOLGE>2</KNOPFFOLGE><KNOPFGRUPPE>EGERAET</KNOPFGRUPPE><KNOPFTEXT>Einbau SMG </KNOPFTEXT><MERKMAL>SMGW-STRINGGROSS</MERKMAL><NACHKOMMA>1</NACHKOMMA><OBERGRENZE>0.0</OBERGRENZE><OBJEKT>140726</OBJEKT><STELLEN>200</STELLEN><TARIF></TARIF><TOLERANZMINUS>0</TOLERANZMINUS><TOLERANZPLUS>0</TOLERANZPLUS><UNTERGRENZE>0.0</UNTERGRENZE><ZWNUMMER></ZWNUMMER><ACT_ID>536145539</ACT_ID>
</ACT>
<ACT> <ALTERG></ALTERG><BEZEICHNER>Geräte im Los</BEZEICHNER><DATALTERG>1899-12-30T00:00:00</DATALTERG><ERG></ERG><FAKTOR>1.000000</FAKTOR><FOLGE>3</FOLGE><HOSTKEY>ZM_KLASSEN</HOSTKEY><KENNZIFFER1> </KENNZIFFER1><KLASSE>MECH</KLASSE><KNOPFFOLGE>1</KNOPFFOLGE><KNOPFGRUPPE>AGERAET</KNOPFGRUPPE><KNOPFTEXT>Ausbau  1EBZ0100020423</KNOPFTEXT><MERKMAL>MECH-INFO</MERKMAL><NACHKOMMA>0</NACHKOMMA><OBERGRENZE>0</OBERGRENZE><OBJEKT>1EBZ0100020423</OBJEKT><STELLEN>0</STELLEN><TARIF></TARIF><TOLERANZMINUS>0</TOLERANZMINUS><TOLERANZPLUS>0</TOLERANZPLUS><UNTERGRENZE>0</UNTERGRENZE><ZWNUMMER></ZWNUMMER><ACT_ID>536145502</ACT_ID>
</ACT>
<ACT> <ALTERG></ALTERG><BEZEICHNER>Gerätenummer</BEZEICHNER><DATALTERG>1899-12-30T00:00:00</DATALTERG><ERG>1EBZ0100020423</ERG><FAKTOR>1.000000</FAKTOR><FOLGE>2</FOLGE><HOSTKEY>ZM_KLASSEN</HOSTKEY><KENNZIFFER1>-</KENNZIFFER1><KLASSE>MECH</KLASSE><KNOPFFOLGE>1</KNOPFFOLGE><KNOPFGRUPPE>AGERAET</KNOPFGRUPPE><KNOPFTEXT>Ausbau  1EBZ0100020423</KNOPFTEXT><MERKMAL>MECH-SERINFO</MERKMAL><NACHKOMMA>0</NACHKOMMA><OBERGRENZE>0</OBERGRENZE><OBJEKT>1EBZ0100020423</OBJEKT><STELLEN>0</STELLEN><TARIF></TARIF><TOLERANZMINUS>0</TOLERANZMINUS><TOLERANZPLUS>0</TOLERANZPLUS><UNTERGRENZE>0</UNTERGRENZE><ZWNUMMER></ZWNUMMER><ACT_ID>536145458</ACT_ID>
</ACT>
<ACT> <ALTERG></ALTERG><BEZEICHNER>Gerätenummer</BEZEICHNER><DATALTERG>1899-12-30T00:00:00</DATALTERG><ERG></ERG><FAKTOR>1.000000</FAKTOR><FOLGE>1</FOLGE><HOSTKEY>ZM_KLASSEN</HOSTKEY><KENNZIFFER1>-</KENNZIFFER1><KLASSE>MECH</KLASSE><KNOPFFOLGE>1</KNOPFFOLGE><KNOPFGRUPPE>EGERAET</KNOPFGRUPPE><KNOPFTEXT>Einbau </KNOPFTEXT><MERKMAL>MECH-SERNR</MERKMAL><NACHKOMMA>0</NACHKOMMA><OBERGRENZE>0</OBERGRENZE><OBJEKT>140728-EB</OBJEKT><STELLEN>99</STELLEN><TARIF></TARIF><TOLERANZMINUS>0</TOLERANZMINUS><TOLERANZPLUS>0</TOLERANZPLUS><UNTERGRENZE>0</UNTERGRENZE><ZWNUMMER></ZWNUMMER><ACT_ID>536145510</ACT_ID>
</ACT>
<ACT> <ALTERG></ALTERG><BEZEICHNER>Gerätenummer</BEZEICHNER><DATALTERG>1899-12-30T00:00:00</DATALTERG><ERG></ERG><FAKTOR>1.000000</FAKTOR><FOLGE>11</FOLGE><HOSTKEY>ZM_KLASSEN</HOSTKEY><KENNZIFFER1>-</KENNZIFFER1><KLASSE>SMGW</KLASSE><KNOPFFOLGE>2</KNOPFFOLGE><KNOPFGRUPPE>EGERAET</KNOPFGRUPPE><KNOPFTEXT>Einbau SMG </KNOPFTEXT><MERKMAL>SMGW-SERNR</MERKMAL><NACHKOMMA>0</NACHKOMMA><OBERGRENZE>0</OBERGRENZE><OBJEKT>140726</OBJEKT><STELLEN>99</STELLEN><TARIF></TARIF><TOLERANZMINUS>0</TOLERANZMINUS><TOLERANZPLUS>0</TOLERANZPLUS><UNTERGRENZE>0</UNTERGRENZE><ZWNUMMER></ZWNUMMER><ACT_ID>536145527</ACT_ID>
</ACT>
<ACT> <ALTERG></ALTERG><BEZEICHNER>Header</BEZEICHNER><DATALTERG>1899-12-30T00:00:00</DATALTERG><ERG> Heike-Petra Lippert</ERG><FAKTOR>1.000000</FAKTOR><FOLGE>0</FOLGE><HOSTKEY>ZM_KLASSEN</HOSTKEY><KENNZIFFER1> </KENNZIFFER1><KLASSE>CHECK</KLASSE><KNOPFFOLGE>1</KNOPFFOLGE><KNOPFGRUPPE>INFO</KNOPFGRUPPE><KNOPFTEXT> Heike-Petra Lippert-1</KNOPFTEXT><MERKMAL>CHECK-HEADER</MERKMAL><NACHKOMMA>0</NACHKOMMA><OBERGRENZE>0</OBERGRENZE><OBJEKT>Anschrift-1</OBJEKT><STELLEN>30</STELLEN><TARIF></TARIF><TOLERANZMINUS>0</TOLERANZMINUS><TOLERANZPLUS>0</TOLERANZPLUS><UNTERGRENZE>0</UNTERGRENZE><ZWNUMMER></ZWNUMMER><ACT_ID>536145549</ACT_ID>
</ACT>
<ACT> <ALTERG></ALTERG><BEZEICHNER>Header</BEZEICHNER><DATALTERG>1899-12-30T00:00:00</DATALTERG><ERG>Ausbau  1EBZ0100020423</ERG><FAKTOR>1.000000</FAKTOR><FOLGE>13</FOLGE><HOSTKEY>ZM_KLASSEN</HOSTKEY><KENNZIFFER1> </KENNZIFFER1><KLASSE>MECH</KLASSE><KNOPFFOLGE>1</KNOPFFOLGE><KNOPFGRUPPE>AGERAET</KNOPFGRUPPE><KNOPFTEXT>Ausbau  1EBZ0100020423</KNOPFTEXT><MERKMAL>MECH-HEADER</MERKMAL><NACHKOMMA>0</NACHKOMMA><OBERGRENZE>0</OBERGRENZE><OBJEKT>1EBZ0100020423</OBJEKT><STELLEN>30</STELLEN><TARIF></TARIF><TOLERANZMINUS>0</TOLERANZMINUS><TOLERANZPLUS>0</TOLERANZPLUS><UNTERGRENZE>0</UNTERGRENZE><ZWNUMMER></ZWNUMMER><ACT_ID>536145456</ACT_ID>
</ACT>
<ACT> <ALTERG></ALTERG><BEZEICHNER>Header</BEZEICHNER><DATALTERG>1899-12-30T00:00:00</DATALTERG><ERG>Einbau </ERG><FAKTOR>1.000000</FAKTOR><FOLGE>13</FOLGE><HOSTKEY>ZM_KLASSEN</HOSTKEY><KENNZIFFER1> </KENNZIFFER1><KLASSE>MECH</KLASSE><KNOPFFOLGE>1</KNOPFFOLGE><KNOPFGRUPPE>EGERAET</KNOPFGRUPPE><KNOPFTEXT>Einbau </KNOPFTEXT><MERKMAL>MECH-HEADER</MERKMAL><NACHKOMMA>0</NACHKOMMA><OBERGRENZE>0</OBERGRENZE><OBJEKT>140728-EB</OBJEKT><STELLEN>30</STELLEN><TARIF></TARIF><TOLERANZMINUS>0</TOLERANZMINUS><TOLERANZPLUS>0</TOLERANZPLUS><UNTERGRENZE>0</UNTERGRENZE><ZWNUMMER></ZWNUMMER><ACT_ID>536145509</ACT_ID>
</ACT>
<ACT> <ALTERG></ALTERG><BEZEICHNER>Header</BEZEICHNER><DATALTERG>1899-12-30T00:00:00</DATALTERG><ERG>Einbau SMG </ERG><FAKTOR>1.000000</FAKTOR><FOLGE>13</FOLGE><HOSTKEY>ZM_KLASSEN</HOSTKEY><KENNZIFFER1> </KENNZIFFER1><KLASSE>SMGW</KLASSE><KNOPFFOLGE>2</KNOPFFOLGE><KNOPFGRUPPE>EGERAET</KNOPFGRUPPE><KNOPFTEXT>Einbau SMG </KNOPFTEXT><MERKMAL>SMGW-HEADER</MERKMAL><NACHKOMMA>0</NACHKOMMA><OBERGRENZE>0</OBERGRENZE><OBJEKT>140726</OBJEKT><STELLEN>30</STELLEN><TARIF></TARIF><TOLERANZMINUS>0</TOLERANZMINUS><TOLERANZPLUS>0</TOLERANZPLUS><UNTERGRENZE>0</UNTERGRENZE><ZWNUMMER></ZWNUMMER><ACT_ID>536145526</ACT_ID>
</ACT>
<ACT> <ALTERG></ALTERG><BEZEICHNER>Header</BEZEICHNER><DATALTERG>1899-12-30T00:00:00</DATALTERG><ERG>Kunde</ERG><FAKTOR>1.000000</FAKTOR><FOLGE>0</FOLGE><HOSTKEY>ZM_KLASSEN</HOSTKEY><KENNZIFFER1> </KENNZIFFER1><KLASSE>CHECK</KLASSE><KNOPFFOLGE>7</KNOPFFOLGE><KNOPFGRUPPE>INFO</KNOPFGRUPPE><KNOPFTEXT>Kunde</KNOPFTEXT><MERKMAL>CHECK-HEADER</MERKMAL><NACHKOMMA>0</NACHKOMMA><OBERGRENZE>0</OBERGRENZE><OBJEKT>KundenRecord</OBJEKT><STELLEN>30</STELLEN><TARIF></TARIF><TOLERANZMINUS>0</TOLERANZMINUS><TOLERANZPLUS>0</TOLERANZPLUS><UNTERGRENZE>0</UNTERGRENZE><ZWNUMMER></ZWNUMMER><ACT_ID>536145560</ACT_ID>
</ACT>
<ACT> <ALTERG></ALTERG><BEZEICHNER>Header</BEZEICHNER><DATALTERG>1899-12-30T00:00:00</DATALTERG><ERG>Verbindung SMWG - mMe</ERG><FAKTOR>1.000000</FAKTOR><FOLGE>13</FOLGE><HOSTKEY>ZM_KLASSEN</HOSTKEY><KENNZIFFER1> </KENNZIFFER1><KLASSE>SMGW</KLASSE><KNOPFFOLGE>4</KNOPFFOLGE><KNOPFGRUPPE>ZUSATZGERAET</KNOPFGRUPPE><KNOPFTEXT>Verbindung SMWG - mMe</KNOPFTEXT><MERKMAL>SMGW-HEADER</MERKMAL><NACHKOMMA>0</NACHKOMMA><OBERGRENZE>0</OBERGRENZE><OBJEKT>140727</OBJEKT><STELLEN>30</STELLEN><TARIF></TARIF><TOLERANZMINUS>0</TOLERANZMINUS><TOLERANZPLUS>0</TOLERANZPLUS><UNTERGRENZE>0</UNTERGRENZE><ZWNUMMER></ZWNUMMER><ACT_ID>536145543</ACT_ID>
</ACT>
<ACT> <ALTERG></ALTERG><BEZEICHNER>Hinweis an Disponent</BEZEICHNER><DATALTERG>1899-12-30T00:00:00</DATALTERG><ERG></ERG><FAKTOR>1.000000</FAKTOR><FOLGE>11</FOLGE><HOSTKEY>ZM_HINWEIS</HOSTKEY><KENNZIFFER1> </KENNZIFFER1><KLASSE></KLASSE><KNOPFFOLGE></KNOPFFOLGE><KNOPFGRUPPE></KNOPFGRUPPE><KNOPFTEXT></KNOPFTEXT><MERKMAL></MERKMAL><NACHKOMMA>0</NACHKOMMA><OBERGRENZE>0</OBERGRENZE><OBJEKT></OBJEKT><STELLEN>0</STELLEN><TARIF></TARIF><TOLERANZMINUS>0</TOLERANZMINUS><TOLERANZPLUS>0</TOLERANZPLUS><UNTERGRENZE>0</UNTERGRENZE><ZWNUMMER></ZWNUMMER><ACT_ID>536145568</ACT_ID>
</ACT>
<ACT> <ALTERG></ALTERG><BEZEICHNER>House_number</BEZEICHNER><DATALTERG>1899-12-30T00:00:00</DATALTERG><ERG>1</ERG><FAKTOR>1.000000</FAKTOR><FOLGE>9</FOLGE><HOSTKEY>ZM_KLASSEN</HOSTKEY><KENNZIFFER1> </KENNZIFFER1><KLASSE>CHECK</KLASSE><KNOPFFOLGE>1</KNOPFFOLGE><KNOPFGRUPPE>INFO</KNOPFGRUPPE><KNOPFTEXT> Heike-Petra Lippert-1</KNOPFTEXT><MERKMAL>CHECK-INFO</MERKMAL><NACHKOMMA>1</NACHKOMMA><OBERGRENZE>0.0</OBERGRENZE><OBJEKT>Anschrift-1</OBJEKT><STELLEN>50</STELLEN><TARIF></TARIF><TOLERANZMINUS>0</TOLERANZMINUS><TOLERANZPLUS>0</TOLERANZPLUS><UNTERGRENZE>0.0</UNTERGRENZE><ZWNUMMER></ZWNUMMER><ACT_ID>536145558</ACT_ID>
</ACT>
<ACT> <ALTERG></ALTERG><BEZEICHNER>Interne Losbezeichung</BEZEICHNER><DATALTERG>1899-12-30T00:00:00</DATALTERG><ERG>E-25-01</ERG><FAKTOR>1.000000</FAKTOR><FOLGE>3</FOLGE><HOSTKEY>ZM_KLASSEN</HOSTKEY><KENNZIFFER1> </KENNZIFFER1><KLASSE>MECH</KLASSE><KNOPFFOLGE>1</KNOPFFOLGE><KNOPFGRUPPE>AGERAET</KNOPFGRUPPE><KNOPFTEXT>Ausbau  1EBZ0100020423</KNOPFTEXT><MERKMAL>MECH-INFO</MERKMAL><NACHKOMMA>0</NACHKOMMA><OBERGRENZE>0</OBERGRENZE><OBJEKT>1EBZ0100020423</OBJEKT><STELLEN>0</STELLEN><TARIF></TARIF><TOLERANZMINUS>0</TOLERANZMINUS><TOLERANZPLUS>0</TOLERANZPLUS><UNTERGRENZE>0</UNTERGRENZE><ZWNUMMER></ZWNUMMER><ACT_ID>536145499</ACT_ID>
</ACT>
<ACT> <ALTERG></ALTERG><BEZEICHNER>Is_active</BEZEICHNER><DATALTERG>1899-12-30T00:00:00</DATALTERG><ERG>true</ERG><FAKTOR>1.000000</FAKTOR><FOLGE>3</FOLGE><HOSTKEY>ZM_KLASSEN</HOSTKEY><KENNZIFFER1> </KENNZIFFER1><KLASSE>CHECK</KLASSE><KNOPFFOLGE>1</KNOPFFOLGE><KNOPFGRUPPE>INFO</KNOPFGRUPPE><KNOPFTEXT> Heike-Petra Lippert-1</KNOPFTEXT><MERKMAL>CHECK-INFO</MERKMAL><NACHKOMMA>1</NACHKOMMA><OBERGRENZE>0.0</OBERGRENZE><OBJEKT>Anschrift-1</OBJEKT><STELLEN>50</STELLEN><TARIF></TARIF><TOLERANZMINUS>0</TOLERANZMINUS><TOLERANZPLUS>0</TOLERANZPLUS><UNTERGRENZE>0.0</UNTERGRENZE><ZWNUMMER></ZWNUMMER><ACT_ID>536145552</ACT_ID>
</ACT>
<ACT> <ALTERG></ALTERG><BEZEICHNER>Is_collective_address</BEZEICHNER><DATALTERG>1899-12-30T00:00:00</DATALTERG><ERG>false</ERG><FAKTOR>1.000000</FAKTOR><FOLGE>10</FOLGE><HOSTKEY>ZM_KLASSEN</HOSTKEY><KENNZIFFER1> </KENNZIFFER1><KLASSE>CHECK</KLASSE><KNOPFFOLGE>1</KNOPFFOLGE><KNOPFGRUPPE>INFO</KNOPFGRUPPE><KNOPFTEXT> Heike-Petra Lippert-1</KNOPFTEXT><MERKMAL>CHECK-INFO</MERKMAL><NACHKOMMA>1</NACHKOMMA><OBERGRENZE>0.0</OBERGRENZE><OBJEKT>Anschrift-1</OBJEKT><STELLEN>50</STELLEN><TARIF></TARIF><TOLERANZMINUS>0</TOLERANZMINUS><TOLERANZPLUS>0</TOLERANZPLUS><UNTERGRENZE>0.0</UNTERGRENZE><ZWNUMMER></ZWNUMMER><ACT_ID>536145559</ACT_ID>
</ACT>
<ACT> <ALTERG></ALTERG><BEZEICHNER>Isthkvjn</BEZEICHNER><DATALTERG>1899-12-30T00:00:00</DATALTERG><ERG>N</ERG><FAKTOR>1.000000</FAKTOR><FOLGE>1</FOLGE><HOSTKEY>ZM_KLASSEN</HOSTKEY><KENNZIFFER1> </KENNZIFFER1><KLASSE>MECH</KLASSE><KNOPFFOLGE>1</KNOPFFOLGE><KNOPFGRUPPE>AGERAET</KNOPFGRUPPE><KNOPFTEXT>Ausbau  1EBZ0100020423</KNOPFTEXT><MERKMAL>MECH-INFO</MERKMAL><NACHKOMMA>0</NACHKOMMA><OBERGRENZE>0</OBERGRENZE><OBJEKT>1EBZ0100020423</OBJEKT><STELLEN>0</STELLEN><TARIF></TARIF><TOLERANZMINUS>0</TOLERANZMINUS><TOLERANZPLUS>0</TOLERANZPLUS><UNTERGRENZE>0</UNTERGRENZE><ZWNUMMER></ZWNUMMER><ACT_ID>536145492</ACT_ID>
</ACT>
<ACT> <ALTERG></ALTERG><BEZEICHNER>Isthkvjn</BEZEICHNER><DATALTERG>1899-12-30T00:00:00</DATALTERG><ERG>N</ERG><FAKTOR>1.000000</FAKTOR><FOLGE>1</FOLGE><HOSTKEY>ZM_KLASSEN</HOSTKEY><KENNZIFFER1> </KENNZIFFER1><KLASSE>SMGW</KLASSE><KNOPFFOLGE>2</KNOPFFOLGE><KNOPFGRUPPE>EGERAET</KNOPFGRUPPE><KNOPFTEXT>Einbau SMG </KNOPFTEXT><MERKMAL>SMGW-INFO</MERKMAL><NACHKOMMA>1</NACHKOMMA><OBERGRENZE>0.0</OBERGRENZE><OBJEKT>140726</OBJEKT><STELLEN>50</STELLEN><TARIF></TARIF><TOLERANZMINUS>0</TOLERANZMINUS><TOLERANZPLUS>0</TOLERANZPLUS><UNTERGRENZE>0.0</UNTERGRENZE><ZWNUMMER></ZWNUMMER><ACT_ID>536145534</ACT_ID>
</ACT>
<ACT> <ALTERG></ALTERG><BEZEICHNER>Kopie erzeugen</BEZEICHNER><DATALTERG>1899-12-30T00:00:00</DATALTERG><ERG></ERG><FAKTOR>1.000000</FAKTOR><FOLGE>6</FOLGE><HOSTKEY>ZM_KOPIE</HOSTKEY><KENNZIFFER1> </KENNZIFFER1><KLASSE></KLASSE><KNOPFFOLGE></KNOPFFOLGE><KNOPFGRUPPE></KNOPFGRUPPE><KNOPFTEXT></KNOPFTEXT><MERKMAL></MERKMAL><NACHKOMMA>0</NACHKOMMA><OBERGRENZE>0</OBERGRENZE><OBJEKT></OBJEKT><STELLEN>0</STELLEN><TARIF></TARIF><TOLERANZMINUS>0</TOLERANZMINUS><TOLERANZPLUS>0</TOLERANZPLUS><UNTERGRENZE>0</UNTERGRENZE><ZWNUMMER></ZWNUMMER><ACT_ID>536145565</ACT_ID>
</ACT>
<ACT> <ALTERG></ALTERG><BEZEICHNER>Kundenbemerkung</BEZEICHNER><DATALTERG>1899-12-30T00:00:00</DATALTERG><ERG>06.06.18 Hil: nicht abrechnen. Vorgang in Klärung&#47;&#47;</ERG><FAKTOR>1.000000</FAKTOR><FOLGE>4</FOLGE><HOSTKEY>ZM_KLASSEN</HOSTKEY><KENNZIFFER1> </KENNZIFFER1><KLASSE>CHECK</KLASSE><KNOPFFOLGE>7</KNOPFFOLGE><KNOPFGRUPPE>INFO</KNOPFGRUPPE><KNOPFTEXT>Kunden Record</KNOPFTEXT><MERKMAL>CHECK-INFO</MERKMAL><NACHKOMMA>1</NACHKOMMA><OBERGRENZE>0.0</OBERGRENZE><OBJEKT>KundenRecord</OBJEKT><STELLEN>50</STELLEN><TARIF></TARIF><TOLERANZMINUS>0</TOLERANZMINUS><TOLERANZPLUS>0</TOLERANZPLUS><UNTERGRENZE>0.0</UNTERGRENZE><ZWNUMMER></ZWNUMMER><ACT_ID>536145564</ACT_ID>
</ACT>
<ACT> <ALTERG></ALTERG><BEZEICHNER>Kundenid</BEZEICHNER><DATALTERG>1899-12-30T00:00:00</DATALTERG><ERG>2946483</ERG><FAKTOR>1.000000</FAKTOR><FOLGE>3</FOLGE><HOSTKEY>ZM_KLASSEN</HOSTKEY><KENNZIFFER1> </KENNZIFFER1><KLASSE>CHECK</KLASSE><KNOPFFOLGE>7</KNOPFFOLGE><KNOPFGRUPPE>INFO</KNOPFGRUPPE><KNOPFTEXT>Kunden Record</KNOPFTEXT><MERKMAL>CHECK-INFO</MERKMAL><NACHKOMMA>1</NACHKOMMA><OBERGRENZE>0.0</OBERGRENZE><OBJEKT>KundenRecord</OBJEKT><STELLEN>50</STELLEN><TARIF></TARIF><TOLERANZMINUS>0</TOLERANZMINUS><TOLERANZPLUS>0</TOLERANZPLUS><UNTERGRENZE>0.0</UNTERGRENZE><ZWNUMMER></ZWNUMMER><ACT_ID>536145563</ACT_ID>
</ACT>
<ACT> <ALTERG></ALTERG><BEZEICHNER>Kundennr</BEZEICHNER><DATALTERG>1899-12-30T00:00:00</DATALTERG><ERG>0014705115</ERG><FAKTOR>1.000000</FAKTOR><FOLGE>2</FOLGE><HOSTKEY>ZM_KLASSEN</HOSTKEY><KENNZIFFER1> </KENNZIFFER1><KLASSE>CHECK</KLASSE><KNOPFFOLGE>7</KNOPFFOLGE><KNOPFGRUPPE>INFO</KNOPFGRUPPE><KNOPFTEXT>Kunden Record</KNOPFTEXT><MERKMAL>CHECK-INFO</MERKMAL><NACHKOMMA>1</NACHKOMMA><OBERGRENZE>0.0</OBERGRENZE><OBJEKT>KundenRecord</OBJEKT><STELLEN>50</STELLEN><TARIF></TARIF><TOLERANZMINUS>0</TOLERANZMINUS><TOLERANZPLUS>0</TOLERANZPLUS><UNTERGRENZE>0.0</UNTERGRENZE><ZWNUMMER></ZWNUMMER><ACT_ID>536145562</ACT_ID>
</ACT>
<ACT> <ALTERG></ALTERG><BEZEICHNER>kVAsy Auftragsnummer</BEZEICHNER><DATALTERG>1899-12-30T00:00:00</DATALTERG><ERG>N-EIN-25-S-000529</ERG><FAKTOR>1.000000</FAKTOR><FOLGE>1</FOLGE><HOSTKEY>ZM_KLASSEN</HOSTKEY><KENNZIFFER1> </KENNZIFFER1><KLASSE>SMGW</KLASSE><KNOPFFOLGE>2</KNOPFFOLGE><KNOPFGRUPPE>EGERAET</KNOPFGRUPPE><KNOPFTEXT>Einbau SMG </KNOPFTEXT><MERKMAL>SMGW-INFO</MERKMAL><NACHKOMMA>1</NACHKOMMA><OBERGRENZE>0.0</OBERGRENZE><OBJEKT>140726</OBJEKT><STELLEN>50</STELLEN><TARIF></TARIF><TOLERANZMINUS>0</TOLERANZMINUS><TOLERANZPLUS>0</TOLERANZPLUS><UNTERGRENZE>0.0</UNTERGRENZE><ZWNUMMER></ZWNUMMER><ACT_ID>536145528</ACT_ID>
</ACT>
<ACT> <ALTERG></ALTERG><BEZEICHNER>kVAsy Auftragsnummer</BEZEICHNER><DATALTERG>1899-12-30T00:00:00</DATALTERG><ERG>N-WEC-25-E-004328</ERG><FAKTOR>1.000000</FAKTOR><FOLGE>1</FOLGE><HOSTKEY>ZM_KLASSEN</HOSTKEY><KENNZIFFER1> </KENNZIFFER1><KLASSE>MECH</KLASSE><KNOPFFOLGE>1</KNOPFFOLGE><KNOPFGRUPPE>AGERAET</KNOPFGRUPPE><KNOPFTEXT>Ausbau  1EBZ0100020423</KNOPFTEXT><MERKMAL>MECH-INFO</MERKMAL><NACHKOMMA>0</NACHKOMMA><OBERGRENZE>0</OBERGRENZE><OBJEKT>1EBZ0100020423</OBJEKT><STELLEN>0</STELLEN><TARIF></TARIF><TOLERANZMINUS>0</TOLERANZMINUS><TOLERANZPLUS>0</TOLERANZPLUS><UNTERGRENZE>0</UNTERGRENZE><ZWNUMMER></ZWNUMMER><ACT_ID>536145459</ACT_ID>
</ACT>
<ACT> <ALTERG></ALTERG><BEZEICHNER>kVAsy Auftragsnummer</BEZEICHNER><DATALTERG>1899-12-30T00:00:00</DATALTERG><ERG>N-WEC-25-E-004328</ERG><FAKTOR>1.000000</FAKTOR><FOLGE>1</FOLGE><HOSTKEY>ZM_KLASSEN</HOSTKEY><KENNZIFFER1> </KENNZIFFER1><KLASSE>MECH</KLASSE><KNOPFFOLGE>1</KNOPFFOLGE><KNOPFGRUPPE>EGERAET</KNOPFGRUPPE><KNOPFTEXT>Einbau </KNOPFTEXT><MERKMAL>MECH-INFO</MERKMAL><NACHKOMMA>0</NACHKOMMA><OBERGRENZE>0</OBERGRENZE><OBJEKT>140728-EB</OBJEKT><STELLEN>0</STELLEN><TARIF></TARIF><TOLERANZMINUS>0</TOLERANZMINUS><TOLERANZPLUS>0</TOLERANZPLUS><UNTERGRENZE>0</UNTERGRENZE><ZWNUMMER></ZWNUMMER><ACT_ID>536145511</ACT_ID>
</ACT>
<ACT> <ALTERG></ALTERG><BEZEICHNER>kVAsy Auftragsnummer</BEZEICHNER><DATALTERG>1899-12-30T00:00:00</DATALTERG><ERG>Verbin2025000534</ERG><FAKTOR>1.000000</FAKTOR><FOLGE>1</FOLGE><HOSTKEY>ZM_KLASSEN</HOSTKEY><KENNZIFFER1> </KENNZIFFER1><KLASSE>SMGW</KLASSE><KNOPFFOLGE>4</KNOPFFOLGE><KNOPFGRUPPE>ZUSATZGERAET</KNOPFGRUPPE><KNOPFTEXT>Verbindung SMWG - mMe</KNOPFTEXT><MERKMAL>SMGW-SERINFO</MERKMAL><NACHKOMMA>0</NACHKOMMA><OBERGRENZE>0</OBERGRENZE><OBJEKT>140727</OBJEKT><STELLEN>0</STELLEN><TARIF></TARIF><TOLERANZMINUS>0</TOLERANZMINUS><TOLERANZPLUS>0</TOLERANZPLUS><UNTERGRENZE>0</UNTERGRENZE><ZWNUMMER></ZWNUMMER><ACT_ID>536145544</ACT_ID>
</ACT>
<ACT> <ALTERG></ALTERG><BEZEICHNER>Losfunktion</BEZEICHNER><DATALTERG>1899-12-30T00:00:00</DATALTERG><ERG>0</ERG><FAKTOR>1.000000</FAKTOR><FOLGE>3</FOLGE><HOSTKEY>ZM_KLASSEN</HOSTKEY><KENNZIFFER1> </KENNZIFFER1><KLASSE>MECH</KLASSE><KNOPFFOLGE>1</KNOPFFOLGE><KNOPFGRUPPE>AGERAET</KNOPFGRUPPE><KNOPFTEXT>Ausbau  1EBZ0100020423</KNOPFTEXT><MERKMAL>MECH-INFO</MERKMAL><NACHKOMMA>0</NACHKOMMA><OBERGRENZE>0</OBERGRENZE><OBJEKT>1EBZ0100020423</OBJEKT><STELLEN>0</STELLEN><TARIF></TARIF><TOLERANZMINUS>0</TOLERANZMINUS><TOLERANZPLUS>0</TOLERANZPLUS><UNTERGRENZE>0</UNTERGRENZE><ZWNUMMER></ZWNUMMER><ACT_ID>536145501</ACT_ID>
</ACT>
<ACT> <ALTERG></ALTERG><BEZEICHNER>Name1</BEZEICHNER><DATALTERG>1899-12-30T00:00:00</DATALTERG><ERG>Heike-Petra Lippert</ERG><FAKTOR>1.000000</FAKTOR><FOLGE>4</FOLGE><HOSTKEY>ZM_KLASSEN</HOSTKEY><KENNZIFFER1> </KENNZIFFER1><KLASSE>CHECK</KLASSE><KNOPFFOLGE>1</KNOPFFOLGE><KNOPFGRUPPE>INFO</KNOPFGRUPPE><KNOPFTEXT> Heike-Petra Lippert-1</KNOPFTEXT><MERKMAL>CHECK-INFO</MERKMAL><NACHKOMMA>1</NACHKOMMA><OBERGRENZE>0.0</OBERGRENZE><OBJEKT>Anschrift-1</OBJEKT><STELLEN>50</STELLEN><TARIF></TARIF><TOLERANZMINUS>0</TOLERANZMINUS><TOLERANZPLUS>0</TOLERANZPLUS><UNTERGRENZE>0.0</UNTERGRENZE><ZWNUMMER></ZWNUMMER><ACT_ID>536145553</ACT_ID>
</ACT>
<ACT> <ALTERG></ALTERG><BEZEICHNER>Name1</BEZEICHNER><DATALTERG>1899-12-30T00:00:00</DATALTERG><ERG>Lippert, Heike-Petra</ERG><FAKTOR>1.000000</FAKTOR><FOLGE>1</FOLGE><HOSTKEY>ZM_KLASSEN</HOSTKEY><KENNZIFFER1> </KENNZIFFER1><KLASSE>CHECK</KLASSE><KNOPFFOLGE>7</KNOPFFOLGE><KNOPFGRUPPE>INFO</KNOPFGRUPPE><KNOPFTEXT>Kunden Record</KNOPFTEXT><MERKMAL>CHECK-INFO</MERKMAL><NACHKOMMA>1</NACHKOMMA><OBERGRENZE>0.0</OBERGRENZE><OBJEKT>KundenRecord</OBJEKT><STELLEN>50</STELLEN><TARIF></TARIF><TOLERANZMINUS>0</TOLERANZMINUS><TOLERANZPLUS>0</TOLERANZPLUS><UNTERGRENZE>0.0</UNTERGRENZE><ZWNUMMER></ZWNUMMER><ACT_ID>536145561</ACT_ID>
</ACT>
<ACT> <ALTERG></ALTERG><BEZEICHNER>Plombe verletzt vorgefunden</BEZEICHNER><DATALTERG>1899-12-30T00:00:00</DATALTERG><ERG></ERG><FAKTOR>1.000000</FAKTOR><FOLGE>1</FOLGE><HOSTKEY>ZM_KLASSEN</HOSTKEY><KENNZIFFER1> </KENNZIFFER1><KLASSE>MECH</KLASSE><KNOPFFOLGE>1</KNOPFFOLGE><KNOPFGRUPPE>AGERAET</KNOPFGRUPPE><KNOPFTEXT>Ausbau  1EBZ0100020423</KNOPFTEXT><MERKMAL>MECH-JANEIN</MERKMAL><NACHKOMMA>0</NACHKOMMA><OBERGRENZE>0</OBERGRENZE><OBJEKT>1EBZ0100020423</OBJEKT><STELLEN>50</STELLEN><TARIF></TARIF><TOLERANZMINUS>0</TOLERANZMINUS><TOLERANZPLUS>0</TOLERANZPLUS><UNTERGRENZE>0</UNTERGRENZE><ZWNUMMER></ZWNUMMER><ACT_ID>536145481</ACT_ID>
</ACT>
<ACT> <ALTERG></ALTERG><BEZEICHNER>Postcode</BEZEICHNER><DATALTERG>1899-12-30T00:00:00</DATALTERG><ERG>38543</ERG><FAKTOR>1.000000</FAKTOR><FOLGE>7</FOLGE><HOSTKEY>ZM_KLASSEN</HOSTKEY><KENNZIFFER1> </KENNZIFFER1><KLASSE>CHECK</KLASSE><KNOPFFOLGE>1</KNOPFFOLGE><KNOPFGRUPPE>INFO</KNOPFGRUPPE><KNOPFTEXT> Heike-Petra Lippert-1</KNOPFTEXT><MERKMAL>CHECK-INFO</MERKMAL><NACHKOMMA>1</NACHKOMMA><OBERGRENZE>0.0</OBERGRENZE><OBJEKT>Anschrift-1</OBJEKT><STELLEN>50</STELLEN><TARIF></TARIF><TOLERANZMINUS>0</TOLERANZMINUS><TOLERANZPLUS>0</TOLERANZPLUS><UNTERGRENZE>0.0</UNTERGRENZE><ZWNUMMER></ZWNUMMER><ACT_ID>536145556</ACT_ID>
</ACT>
<ACT> <ALTERG></ALTERG><BEZEICHNER>Rückmeldegrund</BEZEICHNER><DATALTERG>1899-12-30T00:00:00</DATALTERG><ERG></ERG><FAKTOR>1.000000</FAKTOR><FOLGE>2</FOLGE><HOSTKEY>ZM_RMG</HOSTKEY><KENNZIFFER1> </KENNZIFFER1><KLASSE></KLASSE><KNOPFFOLGE></KNOPFFOLGE><KNOPFGRUPPE></KNOPFGRUPPE><KNOPFTEXT></KNOPFTEXT><MERKMAL></MERKMAL><NACHKOMMA>0</NACHKOMMA><OBERGRENZE>0</OBERGRENZE><OBJEKT></OBJEKT><STELLEN>0</STELLEN><TARIF></TARIF><TOLERANZMINUS>0</TOLERANZMINUS><TOLERANZPLUS>0</TOLERANZPLUS><UNTERGRENZE>0</UNTERGRENZE><ZWNUMMER></ZWNUMMER><ACT_ID>536145453</ACT_ID>
</ACT>
<ACT> <ALTERG></ALTERG><BEZEICHNER>Rückmeldegrund Text</BEZEICHNER><DATALTERG>1899-12-30T00:00:00</DATALTERG><ERG></ERG><FAKTOR>1.000000</FAKTOR><FOLGE>3</FOLGE><HOSTKEY>ZM_RMGTXT</HOSTKEY><KENNZIFFER1> </KENNZIFFER1><KLASSE></KLASSE><KNOPFFOLGE></KNOPFFOLGE><KNOPFGRUPPE></KNOPFGRUPPE><KNOPFTEXT></KNOPFTEXT><MERKMAL></MERKMAL><NACHKOMMA>0</NACHKOMMA><OBERGRENZE>0</OBERGRENZE><OBJEKT></OBJEKT><STELLEN>0</STELLEN><TARIF></TARIF><TOLERANZMINUS>0</TOLERANZMINUS><TOLERANZPLUS>0</TOLERANZPLUS><UNTERGRENZE>0</UNTERGRENZE><ZWNUMMER></ZWNUMMER><ACT_ID>536145454</ACT_ID>
</ACT>
<ACT> <ALTERG></ALTERG><BEZEICHNER>Sachverhalt Freitext</BEZEICHNER><DATALTERG>1899-12-30T00:00:00</DATALTERG><ERG></ERG><FAKTOR>1.000000</FAKTOR><FOLGE>6</FOLGE><HOSTKEY>ZM_SACHVERHALTFREI</HOSTKEY><KENNZIFFER1> </KENNZIFFER1><KLASSE></KLASSE><KNOPFFOLGE></KNOPFFOLGE><KNOPFGRUPPE></KNOPFGRUPPE><KNOPFTEXT></KNOPFTEXT><MERKMAL></MERKMAL><NACHKOMMA>0</NACHKOMMA><OBERGRENZE>0</OBERGRENZE><OBJEKT></OBJEKT><STELLEN>199</STELLEN><TARIF></TARIF><TOLERANZMINUS>0</TOLERANZMINUS><TOLERANZPLUS>0</TOLERANZPLUS><UNTERGRENZE>0</UNTERGRENZE><ZWNUMMER></ZWNUMMER><ACT_ID>536145452</ACT_ID>
</ACT>
<ACT> <ALTERG></ALTERG><BEZEICHNER>Sachverhalt Nr</BEZEICHNER><DATALTERG>1899-12-30T00:00:00</DATALTERG><ERG></ERG><FAKTOR>1.000000</FAKTOR><FOLGE>4</FOLGE><HOSTKEY>ZM_SACHVERHALTNR</HOSTKEY><KENNZIFFER1> </KENNZIFFER1><KLASSE></KLASSE><KNOPFFOLGE></KNOPFFOLGE><KNOPFGRUPPE></KNOPFGRUPPE><KNOPFTEXT></KNOPFTEXT><MERKMAL></MERKMAL><NACHKOMMA>0</NACHKOMMA><OBERGRENZE>0</OBERGRENZE><OBJEKT></OBJEKT><STELLEN>0</STELLEN><TARIF></TARIF><TOLERANZMINUS>0</TOLERANZMINUS><TOLERANZPLUS>0</TOLERANZPLUS><UNTERGRENZE>0</UNTERGRENZE><ZWNUMMER></ZWNUMMER><ACT_ID>536145450</ACT_ID>
</ACT>
<ACT> <ALTERG></ALTERG><BEZEICHNER>Sachverhalt Text</BEZEICHNER><DATALTERG>1899-12-30T00:00:00</DATALTERG><ERG></ERG><FAKTOR>1.000000</FAKTOR><FOLGE>5</FOLGE><HOSTKEY>ZM_SACHVERHALTTXT</HOSTKEY><KENNZIFFER1> </KENNZIFFER1><KLASSE></KLASSE><KNOPFFOLGE></KNOPFFOLGE><KNOPFGRUPPE></KNOPFGRUPPE><KNOPFTEXT></KNOPFTEXT><MERKMAL></MERKMAL><NACHKOMMA>0</NACHKOMMA><OBERGRENZE>0</OBERGRENZE><OBJEKT></OBJEKT><STELLEN>0</STELLEN><TARIF></TARIF><TOLERANZMINUS>0</TOLERANZMINUS><TOLERANZPLUS>0</TOLERANZPLUS><UNTERGRENZE>0</UNTERGRENZE><ZWNUMMER></ZWNUMMER><ACT_ID>536145451</ACT_ID>
</ACT>
<ACT> <ALTERG></ALTERG><BEZEICHNER>Schachtzaehlerjn</BEZEICHNER><DATALTERG>1899-12-30T00:00:00</DATALTERG><ERG>N</ERG><FAKTOR>1.000000</FAKTOR><FOLGE>1</FOLGE><HOSTKEY>ZM_KLASSEN</HOSTKEY><KENNZIFFER1> </KENNZIFFER1><KLASSE>MECH</KLASSE><KNOPFFOLGE>1</KNOPFFOLGE><KNOPFGRUPPE>AGERAET</KNOPFGRUPPE><KNOPFTEXT>Ausbau  1EBZ0100020423</KNOPFTEXT><MERKMAL>MECH-INFO</MERKMAL><NACHKOMMA>0</NACHKOMMA><OBERGRENZE>0</OBERGRENZE><OBJEKT>1EBZ0100020423</OBJEKT><STELLEN>0</STELLEN><TARIF></TARIF><TOLERANZMINUS>0</TOLERANZMINUS><TOLERANZPLUS>0</TOLERANZPLUS><UNTERGRENZE>0</UNTERGRENZE><ZWNUMMER></ZWNUMMER><ACT_ID>536145493</ACT_ID>
</ACT>
<ACT> <ALTERG></ALTERG><BEZEICHNER>Sparte</BEZEICHNER><DATALTERG>1899-12-30T00:00:00</DATALTERG><ERG>E</ERG><FAKTOR>1.000000</FAKTOR><FOLGE>1</FOLGE><HOSTKEY>ZM_KLASSEN</HOSTKEY><KENNZIFFER1> </KENNZIFFER1><KLASSE>MECH</KLASSE><KNOPFFOLGE>1</KNOPFFOLGE><KNOPFGRUPPE>EGERAET</KNOPFGRUPPE><KNOPFTEXT>Einbau </KNOPFTEXT><MERKMAL>MECH-INFO</MERKMAL><NACHKOMMA>0</NACHKOMMA><OBERGRENZE>0</OBERGRENZE><OBJEKT>140728-EB</OBJEKT><STELLEN>0</STELLEN><TARIF></TARIF><TOLERANZMINUS>0</TOLERANZMINUS><TOLERANZPLUS>0</TOLERANZPLUS><UNTERGRENZE>0</UNTERGRENZE><ZWNUMMER></ZWNUMMER><ACT_ID>536145512</ACT_ID>
</ACT>
<ACT> <ALTERG></ALTERG><BEZEICHNER>Sparte</BEZEICHNER><DATALTERG>1899-12-30T00:00:00</DATALTERG><ERG>S</ERG><FAKTOR>1.000000</FAKTOR><FOLGE>1</FOLGE><HOSTKEY>ZM_KLASSEN</HOSTKEY><KENNZIFFER1> </KENNZIFFER1><KLASSE>SMGW</KLASSE><KNOPFFOLGE>2</KNOPFFOLGE><KNOPFGRUPPE>EGERAET</KNOPFGRUPPE><KNOPFTEXT>Einbau SMG </KNOPFTEXT><MERKMAL>SMGW-INFO</MERKMAL><NACHKOMMA>1</NACHKOMMA><OBERGRENZE>0.0</OBERGRENZE><OBJEKT>140726</OBJEKT><STELLEN>50</STELLEN><TARIF></TARIF><TOLERANZMINUS>0</TOLERANZMINUS><TOLERANZPLUS>0</TOLERANZPLUS><UNTERGRENZE>0.0</UNTERGRENZE><ZWNUMMER></ZWNUMMER><ACT_ID>536145538</ACT_ID>
</ACT>
<ACT> <ALTERG></ALTERG><BEZEICHNER>Street</BEZEICHNER><DATALTERG>1899-12-30T00:00:00</DATALTERG><ERG>Rietzer Weg</ERG><FAKTOR>1.000000</FAKTOR><FOLGE>8</FOLGE><HOSTKEY>ZM_KLASSEN</HOSTKEY><KENNZIFFER1> </KENNZIFFER1><KLASSE>CHECK</KLASSE><KNOPFFOLGE>1</KNOPFFOLGE><KNOPFGRUPPE>INFO</KNOPFGRUPPE><KNOPFTEXT> Heike-Petra Lippert-1</KNOPFTEXT><MERKMAL>CHECK-INFO</MERKMAL><NACHKOMMA>1</NACHKOMMA><OBERGRENZE>0.0</OBERGRENZE><OBJEKT>Anschrift-1</OBJEKT><STELLEN>50</STELLEN><TARIF></TARIF><TOLERANZMINUS>0</TOLERANZMINUS><TOLERANZPLUS>0</TOLERANZPLUS><UNTERGRENZE>0.0</UNTERGRENZE><ZWNUMMER></ZWNUMMER><ACT_ID>536145557</ACT_ID>
</ACT>
<ACT> <ALTERG></ALTERG><BEZEICHNER>Unterschrift</BEZEICHNER><DATALTERG>1899-12-30T00:00:00</DATALTERG><ERG></ERG><FAKTOR>1.000000</FAKTOR><FOLGE>5</FOLGE><HOSTKEY>MECH-UNTERSCHRIFT</HOSTKEY><KENNZIFFER1> </KENNZIFFER1><KLASSE>MECH</KLASSE><KNOPFFOLGE>1</KNOPFFOLGE><KNOPFGRUPPE>AGERAET</KNOPFGRUPPE><KNOPFTEXT>Ausbau  1EBZ0100020423</KNOPFTEXT><MERKMAL>MECH-UNTERSCHRIFT</MERKMAL><NACHKOMMA>1</NACHKOMMA><OBERGRENZE>0.0</OBERGRENZE><OBJEKT>1EBZ0100020423</OBJEKT><STELLEN>50</STELLEN><TARIF></TARIF><TOLERANZMINUS>0</TOLERANZMINUS><TOLERANZPLUS>0</TOLERANZPLUS><UNTERGRENZE>0.0</UNTERGRENZE><ZWNUMMER></ZWNUMMER><ACT_ID>536145571</ACT_ID>
</ACT>
<ACT> <ALTERG></ALTERG><BEZEICHNER>Unterschrift</BEZEICHNER><DATALTERG>1899-12-30T00:00:00</DATALTERG><ERG></ERG><FAKTOR>1.000000</FAKTOR><FOLGE>5</FOLGE><HOSTKEY>MECH-UNTERSCHRIFT</HOSTKEY><KENNZIFFER1> </KENNZIFFER1><KLASSE>MECH</KLASSE><KNOPFFOLGE>1</KNOPFFOLGE><KNOPFGRUPPE>EGERAET</KNOPFGRUPPE><KNOPFTEXT>Einbau </KNOPFTEXT><MERKMAL>MECH-UNTERSCHRIFT</MERKMAL><NACHKOMMA>1</NACHKOMMA><OBERGRENZE>0.0</OBERGRENZE><OBJEKT>140728-EB</OBJEKT><STELLEN>50</STELLEN><TARIF></TARIF><TOLERANZMINUS>0</TOLERANZMINUS><TOLERANZPLUS>0</TOLERANZPLUS><UNTERGRENZE>0.0</UNTERGRENZE><ZWNUMMER></ZWNUMMER><ACT_ID>536145572</ACT_ID>
</ACT>
<ACT> <ALTERG></ALTERG><BEZEICHNER>Unterschrift</BEZEICHNER><DATALTERG>1899-12-30T00:00:00</DATALTERG><ERG></ERG><FAKTOR>1.000000</FAKTOR><FOLGE>10</FOLGE><HOSTKEY>ZM_UNTERSCHRIFT</HOSTKEY><KENNZIFFER1> </KENNZIFFER1><KLASSE></KLASSE><KNOPFFOLGE></KNOPFFOLGE><KNOPFGRUPPE></KNOPFGRUPPE><KNOPFTEXT></KNOPFTEXT><MERKMAL></MERKMAL><NACHKOMMA>1</NACHKOMMA><OBERGRENZE>0.0</OBERGRENZE><OBJEKT></OBJEKT><STELLEN>50</STELLEN><TARIF></TARIF><TOLERANZMINUS>0</TOLERANZMINUS><TOLERANZPLUS>0</TOLERANZPLUS><UNTERGRENZE>0.0</UNTERGRENZE><ZWNUMMER></ZWNUMMER><ACT_ID>536145567</ACT_ID>
</ACT>
<ACT> <ALTERG></ALTERG><BEZEICHNER>Verbindung funktionsfähig</BEZEICHNER><DATALTERG>1899-12-30T00:00:00</DATALTERG><ERG></ERG><FAKTOR>1.000000</FAKTOR><FOLGE>5</FOLGE><HOSTKEY>ZM_KLASSEN</HOSTKEY><KENNZIFFER1> </KENNZIFFER1><KLASSE>SMGW</KLASSE><KNOPFFOLGE>4</KNOPFFOLGE><KNOPFGRUPPE>ZUSATZGERAET</KNOPFGRUPPE><KNOPFTEXT>Verbindung SMWG - mMe</KNOPFTEXT><MERKMAL>SMGW-JANEIN</MERKMAL><NACHKOMMA>0</NACHKOMMA><OBERGRENZE>0</OBERGRENZE><OBJEKT>140727</OBJEKT><STELLEN>50</STELLEN><TARIF></TARIF><TOLERANZMINUS>0</TOLERANZMINUS><TOLERANZPLUS>0</TOLERANZPLUS><UNTERGRENZE>0</UNTERGRENZE><ZWNUMMER></ZWNUMMER><ACT_ID>536145548</ACT_ID>
</ACT>
<ACT> <ALTERG></ALTERG><BEZEICHNER>Verbindung Gatewaynummer</BEZEICHNER><DATALTERG>1899-12-30T00:00:00</DATALTERG><ERG></ERG><FAKTOR>1.000000</FAKTOR><FOLGE>3</FOLGE><HOSTKEY>ZM_KLASSEN</HOSTKEY><KENNZIFFER1> </KENNZIFFER1><KLASSE>SMGW</KLASSE><KNOPFFOLGE>4</KNOPFFOLGE><KNOPFGRUPPE>ZUSATZGERAET</KNOPFGRUPPE><KNOPFTEXT>Verbindung SMWG - mMe</KNOPFTEXT><MERKMAL>SMGW-STRING</MERKMAL><NACHKOMMA>1</NACHKOMMA><OBERGRENZE>0.0</OBERGRENZE><OBJEKT>140727</OBJEKT><STELLEN>30</STELLEN><TARIF></TARIF><TOLERANZMINUS>0</TOLERANZMINUS><TOLERANZPLUS>0</TOLERANZPLUS><UNTERGRENZE>0.0</UNTERGRENZE><ZWNUMMER></ZWNUMMER><ACT_ID>536145546</ACT_ID>
</ACT>
<ACT> <ALTERG></ALTERG><BEZEICHNER>Verbindung Typ</BEZEICHNER><DATALTERG>1899-12-30T00:00:00</DATALTERG><ERG></ERG><FAKTOR>1.000000</FAKTOR><FOLGE>4</FOLGE><HOSTKEY>ZM_KLASSEN</HOSTKEY><KENNZIFFER1> </KENNZIFFER1><KLASSE>SMGW</KLASSE><KNOPFFOLGE>4</KNOPFFOLGE><KNOPFGRUPPE>ZUSATZGERAET</KNOPFGRUPPE><KNOPFTEXT>Verbindung SMWG - mMe</KNOPFTEXT><MERKMAL>SMGW-VERBINDUNGTYPBEZ</MERKMAL><NACHKOMMA>0</NACHKOMMA><OBERGRENZE>0</OBERGRENZE><OBJEKT>140727</OBJEKT><STELLEN>0</STELLEN><TARIF></TARIF><TOLERANZMINUS>0</TOLERANZMINUS><TOLERANZPLUS>0</TOLERANZPLUS><UNTERGRENZE>0</UNTERGRENZE><ZWNUMMER></ZWNUMMER><ACT_ID>536145547</ACT_ID>
</ACT>
<ACT> <ALTERG></ALTERG><BEZEICHNER>Verbindung Zählernummer</BEZEICHNER><DATALTERG>1899-12-30T00:00:00</DATALTERG><ERG></ERG><FAKTOR>1.000000</FAKTOR><FOLGE>2</FOLGE><HOSTKEY>ZM_KLASSEN</HOSTKEY><KENNZIFFER1> </KENNZIFFER1><KLASSE>SMGW</KLASSE><KNOPFFOLGE>4</KNOPFFOLGE><KNOPFGRUPPE>ZUSATZGERAET</KNOPFGRUPPE><KNOPFTEXT>Verbindung SMWG - mMe</KNOPFTEXT><MERKMAL>SMGW-STRING</MERKMAL><NACHKOMMA>1</NACHKOMMA><OBERGRENZE>0.0</OBERGRENZE><OBJEKT>140727</OBJEKT><STELLEN>30</STELLEN><TARIF></TARIF><TOLERANZMINUS>0</TOLERANZMINUS><TOLERANZPLUS>0</TOLERANZPLUS><UNTERGRENZE>0.0</UNTERGRENZE><ZWNUMMER></ZWNUMMER><ACT_ID>536145545</ACT_ID>
</ACT>
<ACT> <ALTERG></ALTERG><BEZEICHNER>Zaehlerablesefolge</BEZEICHNER><DATALTERG>1899-12-30T00:00:00</DATALTERG><ERG>390091</ERG><FAKTOR>1.000000</FAKTOR><FOLGE>1</FOLGE><HOSTKEY>ZM_KLASSEN</HOSTKEY><KENNZIFFER1> </KENNZIFFER1><KLASSE>MECH</KLASSE><KNOPFFOLGE>1</KNOPFFOLGE><KNOPFGRUPPE>AGERAET</KNOPFGRUPPE><KNOPFTEXT>Ausbau  1EBZ0100020423</KNOPFTEXT><MERKMAL>MECH-INFO</MERKMAL><NACHKOMMA>0</NACHKOMMA><OBERGRENZE>0</OBERGRENZE><OBJEKT>1EBZ0100020423</OBJEKT><STELLEN>0</STELLEN><TARIF></TARIF><TOLERANZMINUS>0</TOLERANZMINUS><TOLERANZPLUS>0</TOLERANZPLUS><UNTERGRENZE>0</UNTERGRENZE><ZWNUMMER></ZWNUMMER><ACT_ID>536145490</ACT_ID>
</ACT>
<ACT> <ALTERG></ALTERG><BEZEICHNER>Zaehlerablesegebiet</BEZEICHNER><DATALTERG>1899-12-30T00:00:00</DATALTERG><ERG>TK Gruppe 12 Ablesegruppe 4</ERG><FAKTOR>1.000000</FAKTOR><FOLGE>1</FOLGE><HOSTKEY>ZM_KLASSEN</HOSTKEY><KENNZIFFER1> </KENNZIFFER1><KLASSE>MECH</KLASSE><KNOPFFOLGE>1</KNOPFFOLGE><KNOPFGRUPPE>AGERAET</KNOPFGRUPPE><KNOPFTEXT>Ausbau  1EBZ0100020423</KNOPFTEXT><MERKMAL>MECH-INFO</MERKMAL><NACHKOMMA>0</NACHKOMMA><OBERGRENZE>0</OBERGRENZE><OBJEKT>1EBZ0100020423</OBJEKT><STELLEN>0</STELLEN><TARIF></TARIF><TOLERANZMINUS>0</TOLERANZMINUS><TOLERANZPLUS>0</TOLERANZPLUS><UNTERGRENZE>0</UNTERGRENZE><ZWNUMMER></ZWNUMMER><ACT_ID>536145491</ACT_ID>
</ACT>
<ACT> <ALTERG></ALTERG><BEZEICHNER>Zaehlerablesehinweis</BEZEICHNER><DATALTERG>1899-12-30T00:00:00</DATALTERG><ERG>Anschlussraum, Restaurant</ERG><FAKTOR>1.000000</FAKTOR><FOLGE>1</FOLGE><HOSTKEY>ZM_KLASSEN</HOSTKEY><KENNZIFFER1> </KENNZIFFER1><KLASSE>MECH</KLASSE><KNOPFFOLGE>1</KNOPFFOLGE><KNOPFGRUPPE>AGERAET</KNOPFGRUPPE><KNOPFTEXT>Ausbau  1EBZ0100020423</KNOPFTEXT><MERKMAL>MECH-INFO</MERKMAL><NACHKOMMA>0</NACHKOMMA><OBERGRENZE>0</OBERGRENZE><OBJEKT>1EBZ0100020423</OBJEKT><STELLEN>0</STELLEN><TARIF></TARIF><TOLERANZMINUS>0</TOLERANZMINUS><TOLERANZPLUS>0</TOLERANZPLUS><UNTERGRENZE>0</UNTERGRENZE><ZWNUMMER></ZWNUMMER><ACT_ID>536145489</ACT_ID>
</ACT>
<ACT> <ALTERG></ALTERG><BEZEICHNER>Zähler Ablesegebiet</BEZEICHNER><DATALTERG>1899-12-30T00:00:00</DATALTERG><ERG>TK Gruppe 12 Ablesegruppe 4</ERG><FAKTOR>1.000000</FAKTOR><FOLGE>1</FOLGE><HOSTKEY>ZM_KLASSEN</HOSTKEY><KENNZIFFER1> </KENNZIFFER1><KLASSE>MECH</KLASSE><KNOPFFOLGE>1</KNOPFFOLGE><KNOPFGRUPPE>EGERAET</KNOPFGRUPPE><KNOPFTEXT>Einbau </KNOPFTEXT><MERKMAL>MECH-INFO</MERKMAL><NACHKOMMA>0</NACHKOMMA><OBERGRENZE>0</OBERGRENZE><OBJEKT>140728-EB</OBJEKT><STELLEN>0</STELLEN><TARIF></TARIF><TOLERANZMINUS>0</TOLERANZMINUS><TOLERANZPLUS>0</TOLERANZPLUS><UNTERGRENZE>0</UNTERGRENZE><ZWNUMMER></ZWNUMMER><ACT_ID>536145515</ACT_ID>
</ACT>
<ACT> <ALTERG></ALTERG><BEZEICHNER>Zähler Ablesegebiet</BEZEICHNER><DATALTERG>1899-12-30T00:00:00</DATALTERG><ERG></ERG><FAKTOR>1.000000</FAKTOR><FOLGE>1</FOLGE><HOSTKEY>ZM_KLASSEN</HOSTKEY><KENNZIFFER1> </KENNZIFFER1><KLASSE>SMGW</KLASSE><KNOPFFOLGE>2</KNOPFFOLGE><KNOPFGRUPPE>EGERAET</KNOPFGRUPPE><KNOPFTEXT>Einbau SMG </KNOPFTEXT><MERKMAL>SMGW-INFO</MERKMAL><NACHKOMMA>1</NACHKOMMA><OBERGRENZE>0.0</OBERGRENZE><OBJEKT>140726</OBJEKT><STELLEN>50</STELLEN><TARIF></TARIF><TOLERANZMINUS>0</TOLERANZMINUS><TOLERANZPLUS>0</TOLERANZPLUS><UNTERGRENZE>0.0</UNTERGRENZE><ZWNUMMER></ZWNUMMER><ACT_ID>536145541</ACT_ID>
</ACT>
<ACT> <ALTERG></ALTERG><BEZEICHNER>Zählerstand</BEZEICHNER><DATALTERG>1899-12-30T00:00:00</DATALTERG><ERG></ERG><FAKTOR>1.000000</FAKTOR><FOLGE>19</FOLGE><HOSTKEY>ZM_KLASSEN</HOSTKEY><KENNZIFFER1>1-1:1.8.0</KENNZIFFER1><KLASSE>MECH</KLASSE><KNOPFFOLGE>1</KNOPFFOLGE><KNOPFGRUPPE>EGERAET</KNOPFGRUPPE><KNOPFTEXT>Einbau </KNOPFTEXT><MERKMAL>MECH-ZW</MERKMAL><NACHKOMMA>0</NACHKOMMA><OBERGRENZE>0</OBERGRENZE><OBJEKT>140728-EB</OBJEKT><STELLEN>0</STELLEN><TARIF></TARIF><TOLERANZMINUS>0</TOLERANZMINUS><TOLERANZPLUS>0</TOLERANZPLUS><UNTERGRENZE>0</UNTERGRENZE><ZWNUMMER>1</ZWNUMMER><ACT_ID>536145517</ACT_ID>
</ACT>
<ACT> <ALTERG></ALTERG><BEZEICHNER>Zählerstand</BEZEICHNER><DATALTERG>1899-12-30T00:00:00</DATALTERG><ERG></ERG><FAKTOR>1.000000</FAKTOR><FOLGE>19</FOLGE><HOSTKEY>ZM_KLASSEN</HOSTKEY><KENNZIFFER1>1-1:1.8.1</KENNZIFFER1><KLASSE>MECH</KLASSE><KNOPFFOLGE>1</KNOPFFOLGE><KNOPFGRUPPE>EGERAET</KNOPFGRUPPE><KNOPFTEXT>Einbau </KNOPFTEXT><MERKMAL>MECH-ZW</MERKMAL><NACHKOMMA>0</NACHKOMMA><OBERGRENZE>0</OBERGRENZE><OBJEKT>140728-EB</OBJEKT><STELLEN>0</STELLEN><TARIF></TARIF><TOLERANZMINUS>0</TOLERANZMINUS><TOLERANZPLUS>0</TOLERANZPLUS><UNTERGRENZE>0</UNTERGRENZE><ZWNUMMER>2</ZWNUMMER><ACT_ID>536145520</ACT_ID>
</ACT>
<ACT> <ALTERG></ALTERG><BEZEICHNER>Zählerstand</BEZEICHNER><DATALTERG>1899-12-30T00:00:00</DATALTERG><ERG></ERG><FAKTOR>1.000000</FAKTOR><FOLGE>19</FOLGE><HOSTKEY>ZM_KLASSEN</HOSTKEY><KENNZIFFER1>1-1:1.8.2</KENNZIFFER1><KLASSE>MECH</KLASSE><KNOPFFOLGE>1</KNOPFFOLGE><KNOPFGRUPPE>EGERAET</KNOPFGRUPPE><KNOPFTEXT>Einbau </KNOPFTEXT><MERKMAL>MECH-ZW</MERKMAL><NACHKOMMA>0</NACHKOMMA><OBERGRENZE>0</OBERGRENZE><OBJEKT>140728-EB</OBJEKT><STELLEN>0</STELLEN><TARIF></TARIF><TOLERANZMINUS>0</TOLERANZMINUS><TOLERANZPLUS>0</TOLERANZPLUS><UNTERGRENZE>0</UNTERGRENZE><ZWNUMMER>3</ZWNUMMER><ACT_ID>536145522</ACT_ID>
</ACT>
<ACT> <ALTERG></ALTERG><BEZEICHNER>Zählerstand</BEZEICHNER><DATALTERG>1899-12-30T00:00:00</DATALTERG><ERG></ERG><FAKTOR>1.000000</FAKTOR><FOLGE>19</FOLGE><HOSTKEY>ZM_KLASSEN</HOSTKEY><KENNZIFFER1>1-1:2.8.0</KENNZIFFER1><KLASSE>MECH</KLASSE><KNOPFFOLGE>1</KNOPFFOLGE><KNOPFGRUPPE>EGERAET</KNOPFGRUPPE><KNOPFTEXT>Einbau </KNOPFTEXT><MERKMAL>MECH-ZW</MERKMAL><NACHKOMMA>0</NACHKOMMA><OBERGRENZE>0</OBERGRENZE><OBJEKT>140728-EB</OBJEKT><STELLEN>0</STELLEN><TARIF></TARIF><TOLERANZMINUS>0</TOLERANZMINUS><TOLERANZPLUS>0</TOLERANZPLUS><UNTERGRENZE>0</UNTERGRENZE><ZWNUMMER>4</ZWNUMMER><ACT_ID>536145524</ACT_ID>
</ACT>
</OBJ>
</BLOCK>